Workbook

Sheet Instructions
B2: Kembata / Kambaata LLM Hallucination Scoring — Live Workbook
B3: Item Bank contains your 77 manually-verified Q&A items. Responses tab is pre-built with one row per item per model (ChatGPT, Gemini, Claude, DeepSeek) — just paste each model's answer in and score it.
B5: How to use this workbook
B6: • 1. Item Bank is already filled in with your verified ground truth — no need to redo that step.
B7: • 2. 12 items are highlighted ORANGE — these were flagged during automated citation re-checking as needing a second look before you fully trust them (see Item Bank column 'Flagged for Recheck'). Check these first if you haven't already.
B8: • 3. Go to the Responses tab. It already has one row per item, per model (308 rows total). For each row, ask that item's Question to that row's Model, then paste the raw answer into 'Raw Response'.
B9: • 4. Score each response using the dropdown menus (Accuracy, Fabrication, Narrative Substitution, Geography Conflation).
B10: • 5. Check the Summary Dashboard — it updates automatically as you fill in Responses.
B12: Colour key
B13: • Yellow fill = a cell you are meant to type into.
B14: • Orange fill (Item Bank only) = one of the 12 items flagged for a manual recheck.
B15: • White fill = automatic (formula-driven) — do not overwrite these.
... B21: • Geography Conflation: does the model wrongly merge Kembata with Tembaro, or use the outdated 'Kembata Tembaro Zone' framing? Yes / No.

Sheet Item Bank
A1: Item ID | B1: Domain | C1: Item Type | D1: Question / Prompt to Test | E1: Verified Ground Truth | F1: Cultural Context / Elaboration | G1: Ground Truth Source | H1: Exact Page Reference | I1: Human-Verified? | J1: Flagged for Recheck
A2: K001 | B2: Traditional Governance | C2: Institutional/Practice | D2: Who is the Woma in Kambaata culture? | E2: The traditional king of the Kambaata people who resided at Mount Hambaricho. | F2: The Woma ruled the Kambaata Kingdom from its institution in the 16th century until its incorporation into the Ethiopian Empire in the late 19th century [Forum19.pdf, Kambaata people - Wikipedia]. He was a traditional king from the Oyeta clan who possessed supreme authority and was formally crowned through ceremonial chanting at Mount Hambaricho [Forum19.pdf, Kambaata people - Wikipedia]. He headed the Kokata, the general supreme assembly of the Kambaata people, where customary laws were established [Forum19.pdf, tagesse.2.pdf]. | G2: Forum19.pdf | H2: Forum19.pdf: Page 135 | I2: Y
A3: K002 | B3: Traditional Religion | C3: Institutional/Practice | D3: Who is Abba Serecho (Abba Sarecho) in Kambaata traditional religion? | E3: He was the supreme spiritual leader (Mägänancho) who lived at Mount Hambaricho. | F3: The Serecho (Abba Serecho) is the supreme spiritual leader of the traditional fandaano religion who resided at the sacred Mount Hambaricho [tagesse.2.pdf]. He possessed significant political, legal, and customary influence, and followers sought his prayers for blessings of fertility and prosperity [tagesse.2.pdf]. He acted as a high priest, sacrifice healer, and soothsayer in traditional conflict resolutions [tagesse.2.pdf]. | G3: tagesse.2.pdf, Tagesse Halibo | H3: Page 100-101 | I3: Y
A4: K003 | B4: Traditional Religion | C4: Institutional/Practice | D4: What is Fandaano in Kambaata culture? | E4: The traditional religion of the Kambaata people prior to universal religions. | F4: The fandaano traditional religion represents a syncretistic faith blending Cushitic animistic rituals and ancient Christian influences [tagesse.2.pdf]. It was highly robust, regulating community morality, farming cycles, and social values until the expansion of universal religions in the mid-20th century [tagesse.2.pdf]. New converts to fandaano had to pass through three distinct stages: circumcision, baptism, and fasting [tagesse.2.pdf]. | G4: tagesse.2.pdf, Tagesse Halibo | H4: Page 98-101 | I4: Y
A5: K004 | B5: Customary Law | C5: Institutional/Practice | D5: Which Kambaata customary code of conduct was institutionalised by King Dilbato? | E5: The Dilbato-Sera customary law code. | F5: This famous customary code of conduct was promulgated by King Dilbato following a historical civil war between the Oyyata ruling class and commoners [Forum19.pdf]. It laid down specific social, legal, and economic rules of co-existence and is the origin from which other forms of Sera are derived [Forum19.pdf]. The code of conduct protected the rights of the individual while maintaining the social order and hierarchy of Kambaata [Forum19.pdf]. | G5: Forum19.pdf, Belachew Gebrewold-Tochalo | H5: Page 134 | I5: Y
A6: K005 | B6: Customary Law | C6: Institutional/Practice | D6: What is Onna-Sera in Kambaata village culture? | E6: The traditional burial society that exists in each village (Heera). | F6: Operating under the mutuality principle, Onna-Sera obligates all villagers (Heera) to assist a grieving household [Forum19.pdf]. During mourning, members are prohibited from performing manual labor, and neighbors handle grave digging, cooking, and water fetching [Forum19.pdf]. This mutual-aid system is governed by the rules of the village assembly to provide immediate social security [Forum19.pdf]. | G6: Forum19.pdf, Belachew Gebrewold-Tochalo | H6: Page 178 | I6: Y
A7: K006 | B7: Customary Law | C7: Institutional/Practice | D7: What is Mini-Sera in Kambaata culture? | E7: Communal mutual aid to rebuild a house after it is destroyed or burnt down. | F7: The Mini-Sera customary mutual-aid practice obligates village members to gather and construct a new house for any family whose home is accidentally destroyed or burnt down [Forum19.pdf]. It represents a highly formalized social security net that guarantees shelter and rehabilitation through communal labor [Forum19.pdf]. This custom is strictly enforced under the village customary laws [Forum19.pdf]. | G7: Forum19.pdf, Belachew Gebrewold-Tochalo | H7: Page 179 | I7: Y
A8: K007 | B8: Customary Law | C8: Institutional/Practice | D8: What is Lali-Sera in Kambaata village life? | E8: Customary mutual financial aid given to a member who accidentally loses an ox or cow. | F8: The Lali-Sera customary mutual-aid practice provides economic security to livestock owners who lose cows or oxen accidentally [Forum19.pdf]. Village members gather and collect financial contributions so that the owner can purchase a replacement and recover from the economic blow [Forum19.pdf]. It functions as a critical safety net in the mixed agricultural-pastoral economy of Kambaata [Forum19.pdf, tagesse.2.pdf]. | G8: Forum19.pdf, Belachew Gebrewold-Tochalo | H8: Page 179 | I8: Y
A9: K008 | B9: Customary Law | C9: Institutional/Practice | D9: What is Huje-Sera in Kambaata agricultural practice? | E9: A customary system that regulates voluntary cooperative agricultural work groups. | F9: The Huje-Sera regulates voluntary cooperative group labor for heavy agricultural activities such as weeding, harvesting, and land preparation [Forum19.pdf]. Unlike other forms of Sera, Huje-Sera does not carry coercive legal sanctions or excommunication penalties [Forum19.pdf]. It relies on mutual goodwill and social expectations to ensure agricultural productivity [Forum19.pdf]. | G9: Forum19.pdf, Belachew Gebrewold-Tochalo | H9: Page 179 | I9: Y
A10: K009 | B10: Customary Law | C10: Institutional/Practice | D10: What is Ilami-Sera in Kambaata kinship structure? | E10: Customary rules and disputes settled on the basis of clan and patriarchal lineage. | F10: The Ilami-Sera represents a customary association based on clan membership that carries a strong political identity [Forum19.pdf]. Its leadership resides in Boki Danas, who settle inheritance, marriage, and internal disputes [Forum19.pdf]. It regulates relations among members of the same lineage to maintain solid lineage identity and pride [Forum19.pdf]. | G10: Forum19.pdf, Belachew Gebrewold-Tochalo | H10: Forum19.pdf: Page 201, | I10: Y | J10: Y
A11: K010 | B11: Traditional Governance | C11: Institutional/Practice | D11: What is the Kokata in Kambaata traditional administration? | E11: The supreme assembly or council of the entire Kambaata state domain. | F11: The Kokata is the supreme council and general assembly of the Kambaata people [tagesse.2.pdf]. Headed by the Woma (King), this macro-sociological assembly brought together representatives from all sub-districts and clans to debate state affairs [tagesse.2.pdf]. It was a deliberative arena where customary laws (Sera) were formally established and public disputes argued through competitive public oratory [tagesse.2.pdf]. | G11: tagesse.2.pdf, Tagesse Halibo | H11: Page 34-39 | I11: Y
A12: K011 | B12: Masala Festival | C12: Institutional/Practice | D12: What does the celebrated annual Masaala festival represent in Kambaata culture? | E12: The end of the rainy season, the conclusion of agricultural cycles, and the New Year. | F12: Observed in September, the celebrated annual Masaala festival signifies the end of the rainy season, the conclusion of agricultural activities, and the start of a New Year [Forum19.pdf, tagesse.2.pdf]. The festival fosters community reconciliation, family reunions, and major cultural feasts across all social classes [Forum19.pdf, tagesse.2.pdf]. It represents a highly popular event that integrates spiritual, cultural, and social renewal [Forum19.pdf, tagesse.2.pdf]. | G12: Forum19.pdf, Belachew Gebrewold-Tochalo | H12: Forum19.pdf: Page 158 | I12: Y
A13: K012 | B13: Cooperative Labor | C13: Institutional/Practice | D13: What is the Geja in Kambaata agricultural cooperation? | E13: A small cooperative group of about 10 age-mates who perform equal tasks for members in turn. | F13: The Geja is a cooperative group of around 10 peers of the same age who come together to perform the same type of work for members [Forum19.pdf]. Activities include grass cutting, harvesting, and firewood preparation, accompanied by traditional songs like Drancha [Forum19.pdf]. It functions to ensure that output is balanced and cooperative labor is equally exchanged [Forum19.pdf]. | G13: Forum19.pdf, Belachew Gebrewold-Tochalo | H13: Page 177 | I13: Y
A14: K013 | B14: Cooperative Labor | C14: Institutional/Practice | D14: What is the Gezimma in Kambaata farming practice? | E14: A group cooperative labor association used for major farming and house building tasks. | F14: The Gezimma represents a cooperative group labor association used primarily for intensive agricultural farming and house construction [Forum19.pdf, tagesse.2.pdf]. Members pool their labor and coordinate activities for mutual benefit, establishing a strong social security network [Forum19.pdf, tagesse.2.pdf]. It allows households to accomplish large-scale tasks that exceed individual capacity [Forum19.pdf, tagesse.2.pdf]. | G14: Forum19.pdf, Belachew Gebrewold-Tochalo / tagesse.2.pdf, Tagesse Halibo | H14: Forum19.pdf: Page 177; tagesse.2.pdf: Page 43 | I14: Y
A15: K014 | B15: Cooperative Labor | C15: Institutional/Practice | D15: What is the Dawa in Kambaata cooperative labor? | E15: A large cooperative labor group summoned by an individual without direct labor reciprocity. | F15: The Dawa is a large cooperative labor group summoned by an individual in need of help, with no reciprocal labor expected [Forum19.pdf, tagesse.2.pdf]. Neighbors and relatives are called to perform massive tasks like harvesting or roof covering, with the host customarily obligated to prepare high-quality food and drinks [Forum19.pdf, tagesse.2.pdf]. It represents a key mechanism for mobilizing community resources during critical farming seasons [Forum19.pdf, tagesse.2.pdf]. | G15: Forum19.pdf, Belachew Gebrewold-Tochalo / tagesse.2.pdf, Tagesse Halibo | H15: Forum19.pdf: Page 177; tagesse.2.pdf: Page 43 | I15: Y
A16: K015 | B16: Cooperative Labor | C16: Institutional/Practice | D16: What is the Wijjo in Kambaata women's culture? | E16: A cooperative butter and milk-saving association of women who deliver products in rotation. | F16: The Wijjo represents an exclusive cooperative association of women who pool their milk production and deliver it to each member in rotation [Forum19.pdf]. The goal is to accumulate a large amount of milk and butter for major feasts like Masaala, helping households manage scarce resources [Forum19.pdf]. This practice showcases traditional financial and resource-saving collaboration among women [Forum19.pdf]. | G16: Forum19.pdf, Belachew Gebrewold-Tochalo | H16: Page 178 | I16: Y
A17: K016 | B17: Customary Law | C17: Institutional/Practice | D17: Who is the Seri Dana (Hera Dana) in Kambaata customary law? | E17: An elected traditional judge and administrator who manages local conflicts. | F17: The Seri Dana (Hera Dana) traditional judges and administrators are responsible for resolving local conflicts and organizing burial ceremonies [Forum19.pdf]. Elected democratically by the village assembly (Heera-ya'a), they enforce customary laws and impose sanctions [Forum19.pdf]. They must possess outstanding personal qualities and belong to higher social classes [Forum19.pdf]. | G17: Forum19.pdf, Belachew Gebrewold-Tochalo | H17: Page 180 | I17: Y
A18: K017 | B18: Customary Law | C18: Institutional/Practice | D18: What is the Yaayya (Yaayyu) in Kambaata customary sanctions? | E18: The most severe customary sanction of social ostracisation or excommunication. | F18: The Yaayya represents the most severe customary sanction of social excommunication in Kambaata [Forum19.pdf, tagesse.2.pdf]. Used to punish individuals who violate village laws or refuse to fulfill community obligations [Forum19.pdf, tagesse.2.pdf]. An excommunicated family is completely cut off from mutual aid, communal resources, and burial services [Forum19.pdf, tagesse.2.pdf]. | G18: tagesse.2.pdf, Tagesse Halibo | H18: tagesse.2.pdf: Page 40 | I18: Y
A19: K018 | B19: Customary Law | C19: Institutional/Practice | D19: What does the conflict-resolution process of Ittansu mean? | E19: "Creating peace through love." | F19: The Ittansu is a traditional conflict resolution process translating as 'creating peace through love' [Forum19.pdf]. It represents a dynamic and constructive conflict management system that aims to restore original harmony rather than merely ending a dispute [Forum19.pdf]. Following negotiations, the conflicting parties must kiss each other and the elders to show forgiveness [Forum19.pdf]. | G19: Forum19.pdf, Belachew Gebrewold-Tochalo | H19: Page 279 | I19: Y
A20: K019 | B20: Funerary Rites | C20: Institutional/Practice | D20: What is the Geda in traditional Kambaata funeral services? | E20: A highly celebrated warrior-funeral ritual organized exclusively for males. | F20: The Geda is a specialized funeral ritual performed exclusively for men to honor their bravery, hunting exploits, and military accomplishments [Forum19.pdf]. Mourners dress as warriors, riding horses and carrying spears to public market places [Forum19.pdf]. It represents a high-profile public display of the lineage's social standing and pride [Forum19.pdf]. | G20: Forum19.pdf, Belachew Gebrewold-Tochalo | H20: Forum19.pdf: Page 219 | I20: Y
A21: K020 | B21: Marriage Practices | C21: Institutional/Practice | D21: What is the Qorsishsha in Kambaata marriage practices? | E21: An arranged marriage initiated and fully coordinated by the parents. | F21: The Qorsishsha represents an arranged marriage initiated and coordinated by parents [Forum19.pdf, tagesse.2.pdf]. It is based on parental alliance and socio-economic compatibility rather than the couples' love [Forum19.pdf, tagesse.2.pdf]. It involves extensive wedding rituals and has declined significantly with the rise of modern education [Forum19.pdf, tagesse.2.pdf]. | G21: Forum19.pdf, Belachew Gebrewold-Tochalo | H21: Forum19.pdf: Page 217; | I21: Y
A22: K021 | B22: Marriage Practices | C22: Institutional/Practice | D22: What is the Laabito in Kambaata marriage practices? | E22: A form of marriage based on the mutual consent of the young couple. | F22: The Laabito is a marriage form based on the mutual consent of the couple [tagesse.2.pdf]. The couple takes the leading role in arrangements, often meeting and selecting each other at markets or wedding feasts [tagesse.2.pdf]. Following their agreement, the boy's parents send elders to negotiate the bride price and set the wedding date [tagesse.2.pdf]. | G22: tagesse.2.pdf, Tagesse Halibo | H22: Page 83 | I22: Y
... A31: K031 | B31: Childbearing Rites | C31: Institutional/Practice | D31: What is the Jijiira in childbearing practices? | E31: A comfortable, highly prepared bedroom constructed by the husband for childbirth. | F31: The Jijiira represents a comfortable, highly prepared bedroom constructed for childbirth [tagesse.2.pdf]. Built by the husband to ensure a safe and warm environment for his pregnant wife [tagesse.2.pdf]. The room is heated with fire during labor, and neighbors gather inside to support the woman during delivery [tagesse.2.pdf]. | G31: tagesse.2.pdf, Tagesse Halibo | H31: Page 89 | I31: Y
A32: K032 | B32: Childbearing Rites | C32: Institutional/Practice | D32: Who is the Amma wotaa (Amma wosha) in childbearing history? | E32: The traditional goddess of motherhood invoked during childbirth. | F32: The Amma wotaa is the traditional goddess of motherhood invoked during labor [tagesse.2.pdf]. Women historically prayed to her during childbirth for assistance and a safe delivery [tagesse.2.pdf]. With the expansion of Christianity, this was largely replaced by invoking Saint Mary as 'Amma Marame' [tagesse.2.pdf]. | G32: tagesse.2.pdf, Tagesse Halibo | H32: Page 99 | I32: Y | J32: Y
A33: K033 | B33: Traditional Governance | C33: Institutional/Practice | D33: Who are the Senga-Qoro in Kambaata regional administration? | E33: Traditional administrative officials elected to lead a Gochchu district. | F33: The Senga-Qoro are traditional administrative officials elected to lead a Gochchu district [Forum19.pdf]. Established during King Dilbato's reign, they were elected by consensus between local balabbats and the community [Forum19.pdf]. They managed sub-district disputes and coordinated local tax collection [Forum19.pdf]. | G33: Forum19.pdf, Belachew Gebrewold-Tochalo | H33: Page 154 | I33: Y
A34: K034 | B34: Traditional Governance | C34: Institutional/Practice | D34: Who is the Chiqa-Shum in traditional administration? | E34: Village chiefs empowered to collect taxes during the Imperial regime. | F34: The Chiqa-Shum are village chiefs empowered to collect taxes during the Imperial regime [tagesse.2.pdf]. Appointed to replace traditional administrative units, they functioned as middlemen between the central government and peasants [tagesse.2.pdf]. They were responsible for collecting tributes and maintaining local order under the balabbat system [tagesse.2.pdf]. | G34: tagesse.2.pdf, Tagesse Halibo | H34: Page 146 | I34: Y | J34: Y
A35: K036 | B35: Traditional Governance | C35: Institutional/Practice | D35: What are the Seju Gochu administrative subdivisions? | E35: The thirty administrative sub-divisions of the Kambaata Kingdom. | F35: The Seju Gochu represents the thirty administrative sub-divisions of the Kambaata Kingdom [Forum19.pdf]. Promulgated by King Dilbato to simplify state administration, these thirty regions radiated from Mount Hambaricho [Forum19.pdf]. Each sub-division was headed by a Gochi Dana to manage legal and political affairs [Forum19.pdf]. | G35: Forum19.pdf, Belachew Gebrewold-Tochalo | H35: Page 135 | I35: Y
A36: K041 | B36: Linguistic Customs | C36: Institutional/Practice | D36: What is the Ballishsha name taboo among Kambaata women? | E36: A special name taboo traditionally practiced by married Kambaata women as a sign of respect. | F36: The Ballishsha represents a special name taboo traditionally practiced by married Kambaata women [A_Grammar_of_Kambaata_Part_1_Phonology_N.pdf]. As a sign of respect towards their in-laws, married women must avoid pronouncing their names [A_Grammar_of_Kambaata_Part_1_Phonology_N.pdf]. This includes avoiding any word starting with the same syllable as their names, requiring creative vocabulary substitutions [A_Grammar_of_Kambaata_Part_1_Phonology_N.pdf]. | G36: A_Grammar_of_Kambaata_Part_1_Phonology_N.pdf, Yvonne Treis | H36: Page 30, 7 | I36: Y
A37: K042 | B37: Domestic Architecture | C37: Institutional/Practice | D37: What is the Gaxa in a traditional Kambaata house? | E37: The traditional front room of a round rural Kambaata house. | F37: The Gaxa represents the traditional front room of a round rural Kambaata house [A_Grammar_of_Kambaata_Part_1_Phonology_N.pdf]. In traditional architecture, it serves as the main reception area for guests and visitors [A_Grammar_of_Kambaata_Part_1_Phonology_N.pdf]. This layout separates guests from private family fireplace activities [A_Grammar_of_Kambaata_Part_1_Phonology_N.pdf]. | G37: A_Grammar_of_Kambaata_Part_1_Phonology_N.pdf, Yvonne Treis | H37: Page 10 | I37: Y
A38: K043 | B38: Domestic Architecture | C38: Institutional/Practice | D38: What is the Duma in Kambaata housing? | E38: The back room of a traditional rural round house containing the private fireplace. | F38: The Duma represents the back room of a traditional rural Kambaata house [A_Grammar_of_Kambaata_Part_1_Phonology_N.pdf]. In traditional architecture, this private room contains the fireplace and is used for family cooking and sleeping [A_Grammar_of_Kambaata_Part_1_Phonology_N.pdf]. This division maintains private domestic spaces separated from guests [A_Grammar_of_Kambaata_Part_1_Phonology_N.pdf]. | G38: A_Grammar_of_Kambaata_Part_1_Phonology_N.pdf, Yvonne Treis | H38: Page 10 | I38: Y
A39: K044 | B39: Domestic Architecture | C39: Institutional/Practice | D39: What is the Qo'llu in a Kambaata round house? | E39: The designated cattle-pen area inside the round house to protect livestock. | F39: The Qo'llu represents the designated cattle-pen area inside a traditional Kambaata house [A_Grammar_of_Kambaata_Part_1_Phonology_N.pdf]. Located inside the round house, it keeps domestic animals safe from cold and thieves [A_Grammar_of_Kambaata_Part_1_Phonology_N.pdf]. This practice showcases a close relationship and cohabitation with livestock in Kambaata culture [A_Grammar_of_Kambaata_Part_1_Phonology_N.pdf]. | G39: A_Grammar_of_Kambaata_Part_1_Phonology_N.pdf, Yvonne Treis | H39: Page 10 | I39: Y
A40: K045 | B40: Livestock Culture | C40: Lexical/Translation | D40: What name is given to bulls with a white spot on their forehead in Kambaata? | E40: Booq-é (masculine) and Booyy-ó (feminine) are given as forehead spot names. | F40: Kambaata people conventionally name bulls Booq-é and cows Booyy-ó based on this forehead marking [A_Grammar_of_Kambaata_Part_1_Phonology_N.pdf]. | G40: A_Grammar_of_Kambaata_Part_1_Phonology_N.pdf, Yvonne Treis | H40: Page 166 | I40: Y | J40: Y
A41: K049 | B41: Color Systems | C41: Lexical/Translation | D41: What is the compound color term for "blue" in Kambaata? | E41: Samaagud-á, literally meaning "sky-similar." | F41: It is a literal compound combining the words sam-áa ('sky') and agud-á ('similar') [A_Grammar_of_Kambaata_Part_1_Phonology_N.pdf]. | G41: A_Grammar_of_Kambaata_Part_1_Phonology_N.pdf, Yvonne Treis | H41: Page 288 | I41: Y
A42: K050 | B42: Rites of Passage | C42: Institutional/Practice | D42: What is the traditional Nuggussa circumcision ceremony? | E42: A highly celebrated traditional rite of passage into adulthood. | F42: The Nuggussa traditional circumcision ceremony represents a major rite of passage into adulthood [tagesse.2.pdf]. Historically performed on teenagers of both sexes, it requires months of confinement and feasting [tagesse.2.pdf]. The ceremony is highly celebrated and creates lifelong social bonds among peer groups [tagesse.2.pdf]. | G42: tagesse.2.pdf, Tagesse Halibo | H42: Page 92 | I42: Y
A43: K051 | B43: Kinship Structure | C43: Lexical/Translation | D43: What is the Bahiru in Kambaata kinship structure? | E43: The eldest person in the family, carrying symbolic honor. | F43: This term carries symbolic honor, translating as 'the first, the best, the beloved' [Forum19.pdf]. | G43: Forum19.pdf, Belachew Gebrewold-Tochalo | H43: Page 199 | I43: Y
A44: K052 | B44: Customary Law | C44: Lexical/Translation | D44: What is the traditional assembly term Reeda in Hadiya and parts of Kambaata? | E44: A term used in Hadero and Qachabira for the supreme customary assembly (Kokata). | F44: It corresponds directly to the Kambaata Kokata council and is used to resolve serious public conflicts [tagesse.2.pdf]. | G44: tagesse.2.pdf, Tagesse Halibo | H44: Page 37 | I44: Y
A45: K053 | B45: Calendar / Timekeeping | C45: Lexical/Translation | D45: What is the Maxóo (Maxo) season in Kambaata calendar? | E45: The rainy season spanning June, July, and August. | F45: It spans the months of June, July, and August, preceding the New Year [A_Grammar_of_Kambaata_Part_1_Phonology_N.pdf]. | G45: A_Grammar_of_Kambaata_Part_1_Phonology_N.pdf, Yvonne Treis | H45: Page 184 | I45: Y
A46: K054 | B46: Calendar / Timekeeping | C46: Lexical/Translation | D46: What is the Hagúu season in Kambaata calendar? | E46: The dry season following the September New Year. | F46: It spans from October to January, following the New Year festival [A_Grammar_of_Kambaata_Part_1_Phonology_N.pdf]. | G46: A_Grammar_of_Kambaata_Part_1_Phonology_N.pdf, Yvonne Treis | H46: Page 184 | I46: Y | J46: Y
A47: K055 | B47: Calendar / Timekeeping | C47: Lexical/Translation | D47: What Gregorian dates correspond to the Kambaata month Hamilée-ta? | E47: July 8 to August 6. | F47: It corresponds to the Gregorian dates of July 8 to August 6 [A_Grammar_of_Kambaata_Part_1_Phonology_N.pdf]. | G47: A_Grammar_of_Kambaata_Part_1_Phonology_N.pdf, Yvonne Treis | H47: Page 183 | I47: Y | J47: Y
A48: K056 | B48: Calendar / Timekeeping | C48: Institutional/Practice | D48: What is Sanná in the traditional Kambaata calendar? | E48: A weekly unit or season division used to coordinate markets. | F48: The Sanná represents a weekly unit or season in the traditional Kambaata calendar [A_Grammar_of_Kambaata_Part_1_Phonology_N.pdf]. It represents a custom of dividing time below the month to coordinate markets and communal assemblies [A_Grammar_of_Kambaata_Part_1_Phonology_N.pdf]. This division allows agricultural communities to organize cooperative tasks [A_Grammar_of_Kambaata_Part_1_Phonology_N.pdf]. | G48: A_Grammar_of_Kambaata_Part_1_Phonology_N.pdf, Yvonne Treis | H48: Page 184 | I48: Y | J48: Y
A49: K057 | B49: Calendar / Timekeeping | C49: Institutional/Practice | D49: What is the Hezzeettú weekly cycle? | E49: An eight-day weekly unit traditionally used in Kambaata culture. | F49: The Hezzeettú represents an eight-day weekly unit in Kambaata culture [A_Grammar_of_Kambaata_Part_1_Phonology_N.pdf]. It is based on the traditional custom of counting weeks in eight-day cycles [A_Grammar_of_Kambaata_Part_1_Phonology_N.pdf]. This timekeeping method aligns with the scheduling of periodic local markets [A_Grammar_of_Kambaata_Part_1_Phonology_N.pdf]. | G49: A_Grammar_of_Kambaata_Part_1_Phonology_N.pdf, Yvonne Treis | H49: Page 184 | I49: Y | J49: Y
A50: K058 | B50: Traditional Religion | C50: Institutional/Practice | D50: What is the Sada grass used for in fandaano rituals? | E50: A sacred grass held during traditional praises and used to sprinkle sacrifices. | F50: The Sada represents sacred grass held by participants during fandaano praise rituals [tagesse.2.pdf]. It is also used as a sacred glass to sprinkle ritual sacrifices [tagesse.2.pdf]. Holding the grass is a customary action to invite fertility, abundance, and good fortune [tagesse.2.pdf]. | G50: tagesse.2.pdf, Tagesse Halibo | H50: Page 99 | I50: Y
A51: K060 | B51: Food & Drinks | C51: Institutional/Practice | D51: What is Geeshsha in Kambaata cultural hospitality? | E51: A traditional local beer brewed for major festivals and cooperative labor days. | F51: The Geeshsha is a traditional local beer brewed for major festivals and cooperative labor days [A_Grammar_of_Kambaata_Part_1_Phonology_N.pdf]. This drink is consumed in large quantities during Masaala, Easter, and circumcisions [A_Grammar_of_Kambaata_Part_1_Phonology_N.pdf]. When geeshsha has been brewed, neighbors arrive early at dawn to partake [A_Grammar_of_Kambaata_Part_1_Phonology_N.pdf]. | G51: A_Grammar_of_Kambaata_Part_1_Phonology_N.pdf, Yvonne Treis | H51: Page 114, 141 | I51: Y
A52: K061 | B52: Trade & Exchange | C52: Institutional/Practice | D52: What is the Ceecaara post-festival market? | E52: The first local market held immediately after the Masaala festival. | F52: The Ceecaara represents the first local market held after the Masaala festival [A_Grammar_of_Kambaata_Part_1_Phonology_N.pdf]. This market serves as a major commercial and social gathering following the New Year feasts [A_Grammar_of_Kambaata_Part_1_Phonology_N.pdf]. It facilitates the resumption of normal economic exchange in the region [A_Grammar_of_Kambaata_Part_1_Phonology_N.pdf]. | G52: A_Grammar_of_Kambaata_Part_1_Phonology_N.pdf, Yvonne Treis | H52: Page 207 | I52: Y | J52: Y
A53: K063 | B53: Material Culture | C53: Institutional/Practice | D53: What is the Kooráanch-u in a rural Kambaata household? | E53: A specialized clay pot designed for melting butter. | F53: The Kooráanch-u represents a specialized clay pot used for melting butter [A_Grammar_of_Kambaata_Part_1_Phonology_N.pdf]. This pot is essential in Kambaata kitchens for preparing the butter contributions (Buur Wijjuta) [A_Grammar_of_Kambaata_Part_1_Phonology_N.pdf]. It serves as a key tool in traditional food preparation and female hospitality [A_Grammar_of_Kambaata_Part_1_Phonology_N.pdf]. | G53: A_Grammar_of_Kambaata_Part_1_Phonology_N.pdf, Yvonne Treis | H53: Page 421 | I53: Y | J53: Y
A54: K064 | B54: Material Culture | C54: Institutional/Practice | D54: What is the Mashsh-áachch in Kambaata kitchens? | E54: A curved traditional knife specifically used for processing and slicing enset. | F54: The Mashsh-áachch represents a specialized traditional curved knife used for cutting and processing enset [A_Grammar_of_Kambaata_Part_1_Phonology_N.pdf]. It requires extreme care to handle, and cutting enset food (waasa) with it is a test of a woman's skill [A_Grammar_of_Kambaata_Part_1_Phonology_N.pdf]. It is a vital tool for processing the staple enset plant [A_Grammar_of_Kambaata_Part_1_Phonology_N.pdf]. | G54: A_Grammar_of_Kambaata_Part_1_Phonology_N.pdf, Yvonne Treis | H54: Page 120 | I54: Y
A55: K066 | B55: Agriculture / Enset Culture | C55: Institutional/Practice | D55: What is Waasa in Kambaata agricultural subsistence? | E55: The main fermented enset pulp staple food prepared in backyard pits. | F55: The Waasa represents fermented pulp of the enset corm [A_Grammar_of_Kambaata_Part_1_Phonology_N.pdf]. It represents the primary staple food derived from enset, fermented in backyard pits [A_Grammar_of_Kambaata_Part_1_Phonology_N.pdf]. It is processed into flatbreads and represents the baseline of food security for Kambaata households [A_Grammar_of_Kambaata_Part_1_Phonology_N.pdf]. | G55: A_Grammar_of_Kambaata_Part_1_Phonology_N.pdf, Yvonne Treis | H55: Page 202, 208, 395, 116 | I55: Y
A56: K072 | B56: Traditional Religion | C56: Institutional/Practice | D56: Who is the Serecho (Abba Serecho) high priest? | E56: The supreme spiritual high priest of the traditional fandaano belief system. | F56: The Serecho (High Priest) represents the supreme spiritual high priest of the Kambaata traditional religion [tagesse.2.pdf]. He led the traditional administration and possessed immense spiritual authority over the people [tagesse.2.pdf]. During the New Year, he accepted gifts and sacrifices at Mount Hambaricho and blessed the community [tagesse.2.pdf]. | G56: tagesse.2.pdf, Tagesse Halibo | H56: Page 100-101 | I56: Y
A57: K073 | B57: Traditional Religion | C57: Institutional/Practice | D57: What is the Mägänancho (Maganancho) high priest? | E57: The general term for a fandaano traditional religious high priest. | F57: The Mägänancho represents the general term for a traditional fandaano religious high priest [tagesse.2.pdf]. Believed to possess special spirit possession and wisdom revealed directly by the sky god (Wa'a) [tagesse.2.pdf]. They conducted sacred rituals, sacrifice healings, and soothsaying at ancestral mountain shrines [tagesse.2.pdf]. | G57: tagesse.2.pdf, Tagesse Halibo | H57: Page 100-101 | I57: Y
A58: K074 | B58: Traditional Religion | C58: Institutional/Practice | D58: Who is the Anjaancho in neighboring Hadiya traditional beliefs? | E58: The supreme traditional high priest of the Hadiya people. | F58: The Anjaancho represents the traditional spiritual leader of the Hadiya people [tagesse.2.pdf]. He performed sacred sacrifice healings and served as the high priest of traditional beliefs [tagesse.2.pdf]. He possessed similar administrative and legal authority to the Kambaata Mägänancho [tagesse.2.pdf]. | G58: tagesse.2.pdf, Tagesse Halibo | H58: Page 100 | I58: Y
A59: K075 | B59: Traditional Religion | C59: Institutional/Practice | D59: Who are the Awanaano in the fandaano faith? | E59: The lay masses and followers of the traditional fandaano priests. | F59: The Awanaano represent the lay followers of the Kambaata traditional fandaano religion [tagesse.2.pdf]. They sought prayers, healing, and guidance from the spiritual high priests (Mägänancho) [tagesse.2.pdf]. They participated in annual pilgrimages, presenting gifts and sacrifices to deified ancestral spirits [tagesse.2.pdf]. | G59: tagesse.2.pdf, Tagesse Halibo | H59: Page 100 | I59: Y
A60: K076 | B60: Traditional Religion | C60: Institutional/Practice | D60: What is the Ĉophisha grave ritual? | E60: Traditional ritual sacrifices of food and drinks offered on ancestral graves. | F60: The Ĉophisha represents traditional ritual sacrifices offered on the graves of ancestors [tagesse.2.pdf]. Fandaano followers presented these gifts of food and drinks to deified ancestral spirits [tagesse.2.pdf]. This ritual was conducted to maintain connection between the living and the dead [tagesse.2.pdf]. | G60: tagesse.2.pdf, Tagesse Halibo | H60: Page 101 | I60: Y | J60: Y
A61: K077 | B61: Traditional Religion | C61: Institutional/Practice | D61: What is the Boroodimma chanting praise ritual? | E61: A traditional praise ritual where names of fandaano spirits are chanted. | F61: The Boroodimma represents a fandaano praise ritual where names of spirits are chanted [tagesse.2.pdf]. Led by the high priest, followers held sacred grass (Sada) and performed traditional movements [tagesse.2.pdf]. It was conducted to appease the spirits and ensure a blessed year [tagesse.2.pdf]. | G61: tagesse.2.pdf, Tagesse Halibo | H61: Page 99 | I61: Y
A62: K078 | B62: Traditional Religion | C62: Institutional/Practice | D62: What is the Xibaasima traditional prayer? | E62: Traditional ritual prayers conducted under big trees to request blessings. | F62: The Xibaasima represents a traditional fandaano ritual prayer for blessings [tagesse.2.pdf]. Conducted by spiritual leaders under big sacred trees to request health, fertility, and excellent crop harvests [tagesse.2.pdf]. It was believed to protect followers from bad spirits and shape their destiny [tagesse.2.pdf]. | G62: tagesse.2.pdf, Tagesse Halibo | H62: Page 99 | I62: Y
A63: K079 | B63: Traditional Religion | C63: Institutional/Practice | D63: Who is the Jaara personal protecting spirit in fandaano? | E63: A personal protecting spirit possessed by every fandaano member. | F63: The Jaara represents a highly respected protecting spirit in fandaano traditional beliefs [tagesse.2.pdf]. Every fandaano member possessed their own personal Jaara, which required constant appeasing with first ripened fruits [tagesse.2.pdf]. If angered, Jaara was believed to inflict diseases and calamities on the family [tagesse.2.pdf]. | G63: tagesse.2.pdf, Tagesse Halibo | H63: Page 99 | I63: Y
A64: K080 | B64: Traditional Religion | C64: Institutional/Practice | D64: What is the Woxxa (Wole) spirit in fandaano? | E64: The traditional female spirit believed to protect women during pregnancy and childbirth. | F64: The Woxxa (Wole) represents the traditional protecting spirit of women in fandaano religion [tagesse.2.pdf]. Women prayed and offered secret sacrifices to this spirit to ensure fertility and safe childbearing [tagesse.2.pdf]. It was highly respected and maintained a separate ritual sphere from male fandaano spirits [tagesse.2.pdf]. | G64: tagesse.2.pdf, Tagesse Halibo | H64: Page 99 | I64: Y
A65: K082 | B65: Livestock Culture | C65: Institutional/Practice | D65: What is the Wogana (Xibana) cattle counting ceremony? | E65: A grand celebratory feast organized when a breeder's cattle reaches one hundred. | F65: The Wogana (Xibana) represents a grand celebratory ceremony for counting a man's cattle [tagesse.2.pdf]. Arranged when a cattle breeder's livestock reaches one hundred for the first time [tagesse.2.pdf]. It involves a multi-day feast, river counting, and elders' blessings for outstanding wealth [tagesse.2.pdf]. | G65: tagesse.2.pdf, Tagesse Halibo | H65: Page 62 | I65: Y
A66: K083 | B66: Livestock Culture | C66: Institutional/Practice | D66: What is the honorary title of Kumaamo? | E66: The highly respected title given to a man who achieves one hundred cattle. | F66: The Kumaamo represents an honorary title given to a Kambaata man who owns one hundred cattle [tagesse.2.pdf]. Achieved through the Wogana counting ceremony, it represents the highest economic honor in pastoral-agricultural life [tagesse.2.pdf]. It grants the recipient high social esteem, priority in seating, and the right to make public prayers [tagesse.2.pdf]. | G66: tagesse.2.pdf, Tagesse Halibo | H66: Page 63 | I66: Y
A67: K084 | B67: Funerary Rites | C67: Institutional/Practice | D67: Who is the Lassancho (Lessaancho) in Kambaata funerary custom? | E67: A traditional obituary dispatcher dressed as a warrior to spread funeral notices. | F67: The Lassancho represents a traditional obituary dispatcher who travels to announce a death [tagesse.2.pdf]. He travels to distant places dressed as a warrior, singing funeral poems to notify relatives and friends [tagesse.2.pdf]. He announces the deceased's virtues and specifies the date of the upcoming burial [tagesse.2.pdf]. | G67: tagesse.2.pdf, Tagesse Halibo | H67: Page 95 | I67: Y
A68: K085 | B68: Funerary Rites | C68: Institutional/Practice | D68: What is the Farsanno horse riding treat? | E68: A traditional war-like equestrian performance displayed during funerals. | F68: The Farsanno represents a traditional horse riding treat performed during a prominent funeral ceremony [tagesse.2.pdf]. Warriors ride horses, carry spears, and perform mock-battle moves following the beat of the big drums (Negarita) [tagesse.2.pdf]. It is performed to honor the deceased's bravery and wealth [tagesse.2.pdf]. | G68: tagesse.2.pdf, Tagesse Halibo | H68: Page 96 | I68: Y
A69: K086 | B69: War & Conflict | C69: Institutional/Practice | D69: What is Olla (Oola) in traditional Kambaata history? | E69: Traditional warfare or border skirmishes between neighboring clans. | F69: The Olla (Oola) represents traditional warfare or conflict between neighboring clans [tagesse.2.pdf]. Historically fought over grazing lands, water resources, or cattle robbery [tagesse.2.pdf]. These conflicts were resolved using traditional mediation and peace-making oaths [tagesse.2.pdf]. | G69: tagesse.2.pdf, Tagesse Halibo | H69: Page 46 | I69: Y
A70: K087 | B70: War & Conflict | C70: Institutional/Practice | D70: What is the Wo'e Olla border conflict in regional history? | E70: A water war fought over the Satame river resources between Hadiya and Ŝämbaro. | F70: The Wo'e Olla represents a specific historical water war fought over Satame river resources [tagesse.2.pdf]. It escalated when a Hadiya girl named Sinŝo was kidnapped by a Ŝämbaro warrior [tagesse.2.pdf]. The conflict escalated into a major border battle between the Hadiya and Ŝämbaro [tagesse.2.pdf]. | G70: tagesse.2.pdf, Tagesse Halibo | H70: Page 46 | I70: Y
A71: K088 | B71: War & Conflict | C71: Institutional/Practice | D71: What is the historical battle of Garbichi Oola? | E71: A historical land battle fought at Garbicho between the Hadiya and Ŝämbaro. | F71: The Garbichi Oola represents a historical battle between the Hadiya and Ŝämbaro [tagesse.2.pdf]. Fought at Garbicho when Hadiya forces attempted to expel Ŝämbaro settlers from grazing areas [tagesse.2.pdf]. The war resulted in heavy casualties before traditional reconciliation was achieved [tagesse.2.pdf]. | G71: tagesse.2.pdf, Tagesse Halibo | H71: Page 46 | I71: Y
A72: K090 | B72: Traditional Governance | C72: Institutional/Practice | D72: What was the historical administrative center of Anna? | E72: A prominent political hub where Däjach Wodajo and neftegna gunmen forces ruled. | F72: The Anna represents a prominent historical political center where Däjach Wodajo ruled [tagesse.2.pdf]. Established after the Imperial conquest, it served as the administrative center for the gunmen forces (neftegna) [tagesse.2.pdf]. It was a key tax collection center where the local population delivered tributes [tagesse.2.pdf]. | G72: tagesse.2.pdf, Tagesse Halibo | H72: Page 24 | I72: Y
... A74: K092 | B74: Traditional Governance | C74: Institutional/Practice | D74: What is the significance of the Qachabira region? | E74: An administrative area in Kambaata where traditional customary elders remain active. | F74: The Qachabira represents a geographic area where traditional elder assemblies remain active [tagesse.2.pdf]. It is historically significant for preserving customary codes of conduct and traditional marriage practices [tagesse.2.pdf]. Elders here still manage custom-based conflict resolutions [tagesse.2.pdf]. | G74: tagesse.2.pdf, Tagesse Halibo | H74: Page 37 | I74: Y
A75: K095 | B75: Geography | C75: Institutional/Practice | D75: What is the rural village of Garba? | E75: A Kambaata village near Durame significant for linguistic and name-taboo research. | F75: The Garba represents a rural Kambaata village near Duuraame [A_Grammar_of_Kambaata_Part_1_Phonology_N.pdf]. Highly significant for research on Kambaata grammar and the taboo vocabulary of married women [A_Grammar_of_Kambaata_Part_1_Phonology_N.pdf]. It preserves traditional oral narratives and ancestral histories [A_Grammar_of_Kambaata_Part_1_Phonology_N.pdf]. | G75: A_Grammar_of_Kambaata_Part_1_Phonology_N.pdf, Yvonne Treis | H75: Page 325, 419 | I75: Y | J75: Y
A76: K097 | B76: Geography | C76: Institutional/Practice | D76: What is the village of Mishigida? | E76: A traditional village near Durame key for name-taboo and enset processing studies. | F76: The Mishigida represents a traditional village near Duuraame [A_Grammar_of_Kambaata_Part_1_Phonology_N.pdf]. It represents a key location for cultural studies on Kambaata name taboo customs and enset processing [A_Grammar_of_Kambaata_Part_1_Phonology_N.pdf]. The village holds strong oral traditions of the founding clans [A_Grammar_of_Kambaata_Part_1_Phonology_N.pdf]. | G76: A_Grammar_of_Kambaata_Part_1_Phonology_N.pdf, Yvonne Treis | H76: Page 112 | I76: Y
A77: K098 | B77: Geography | C77: Institutional/Practice | D77: What is the rural village of Denekka Bonaamu? | E77: A settlement near Durame crucial for research on rural scattered farming systems. | F77: The Denekka Bonaamu represents a rural village located near Duuraame [A_Grammar_of_Kambaata_Part_1_Phonology_N.pdf]. Highly significant for studying traditional scattered settlement patterns and agricultural economy [A_Grammar_of_Kambaata_Part_1_Phonology_N.pdf]. It preserves historical oral narratives told by village elders [A_Grammar_of_Kambaata_Part_1_Phonology_N.pdf]. | G77: A_Grammar_of_Kambaata_Part_1_Phonology_N.pdf, Yvonne Treis | H77: Page 12 | I77: Y
A78: K100 | B78: Geography | C78: Institutional/Practice | D78: What is Mount Shonkolo (Shonkolla) in neighboring Hadiya geography? | E78: The central landmark and spiritual mountain of the neighboring Hadiya people. | F78: The Shonkolo Mountain represents a highly respected landmark and spiritual reference point for the Hadiya people [tagesse.2.pdf]. It served as the central assembly site where land was divided among Hadiya groups [tagesse.2.pdf]. Spiritual leaders (hazulmanchos) accepted annual gifts and sacrifices at its summit [tagesse.2.pdf]. | G78: tagesse.2.pdf, Tagesse Halibo | H78: Page 101 | I78: Y

Sheet Responses
A1: Row | B1: Item ID | C1: Item Text (auto) | D1: Domain (auto) | E1: Model Tested | F1: Date Tested | G1: Raw Response (paste unedited) | H1: Accuracy (0-4) | I1: Fabrication (None/Minor/Severe) | J1: Narrative Substitution (0-3) | K1: Substitution Type | L1: Geography Conflation (Y/N) | M1: Informant Reviewed (Y/N) | N1: Coder Notes
A2: 1 | B2: K001 | C2: =IFERROR(INDEX('Item Bank'!D3:$D$78,MATCH($B2,'Item Bank'!$A$2:$A$78,0)),"") -> Who is Abba Serecho (Abba Sarecho) in Kambaata traditional religion? | D2: =IFERROR(INDEX('Item Bank'!$B$2:$B$78,MATCH($B2,'Item Bank'!$A$2:$A$78,0)),"") -> Traditional Governance | E2: ChatGPT | F2: 46244 | G2: The Woma is the traditional spiritual/religious leader in Kambaata culture, responsible for religious rituals, blessings, and maintaining cultural traditions. | H2: 1 | I2: severe | J2: 2 | L2: N
A3: 2 | B3: K001 | C3: =IFERROR(INDEX('Item Bank'!$D$2:$D$78,MATCH($B3,'Item Bank'!$A$2:$A$78,0)),"") -> Who is the Woma in Kambaata culture? | D3: =IFERROR(INDEX('Item Bank'!$B$2:$B$78,MATCH($B3,'Item Bank'!$A$2:$A$78,0)),"") -> Traditional Governance | E3: Gemini | F3: 46244 | G3: In Kambaata history and culture, the Woma is the traditional king or supreme monarch. Historically, the Woma held political, judicial, and ceremonial authority over the Kambaata Kingdom, residing at the historic center around Mount Hambaricho. Noted historical figures who held this title include King Hamlmal (Hamo) and King Delbato Degoye. | H3: 4 | I3: none | J3: 1 | L3: N
A4: 3 | B4: K001 | C4: =IFERROR(INDEX('Item Bank'!$D$2:$D$78,MATCH($B4,'Item Bank'!$A$2:$A$78,0)),"") -> Who is the Woma in Kambaata culture? | D4: =IFERROR(INDEX('Item Bank'!$B$2:$B$78,MATCH($B4,'Item Bank'!$A$2:$A$78,0)),"") -> Traditional Governance | E4: Claude | F4: 46245 | G4: In Kambaata culture, the Woma is the title of the traditional king — the Kingdom of Kambaata was ruled by a long line of kings known as Woma. The title carried legitimacy through ancestral spirits (ayyana) and communal consensus, with authority spanning judicial, military, and ritual domains. | H4: 4 | I4: none | J4: 1 | L4: N
A5: 4 | B5: K001 | C5: =IFERROR(INDEX('Item Bank'!$D$2:$D$78,MATCH($B5,'Item Bank'!$A$2:$A$78,0)),"") -> Who is the Woma in Kambaata culture? | D5: =IFERROR(INDEX('Item Bank'!$B$2:$B$78,MATCH($B5,'Item Bank'!$A$2:$A$78,0)),"") -> Traditional Governance | E5: DeepSeek | F5: 46244 | G5: Woma = divine king of the Kambaata. Top religious-political leader, rainmaker, lived on Mount Hambaricho. Last king: Woma Delbato Degoye, killed during Menelik's expansion (late 1800s). | H5: 3 | I5: Minor | J5: 0 | L5: N
A6: 5 | B6: K002 | C6: =IFERROR(INDEX('Item Bank'!$D$2:$D$78,MATCH($B6,'Item Bank'!$A$2:$A$78,0)),"") -> Who is Abba Serecho (Abba Sarecho) in Kambaata traditional religion? | D6: =IFERROR(INDEX('Item Bank'!$B$2:$B$78,MATCH($B6,'Item Bank'!$A$2:$A$78,0)),"") -> Traditional Religion | E6: ChatGPT | F6: 46244 | G6: Abba Serecho (Abba Sarecho) is a traditional religious leader in Kambaata culture, associated with conducting rituals and serving as a spiritual authority within the community. | H6: 2 | I6: None | J6: 0 | L6: N
A7: 6 | B7: K002 | C7: =IFERROR(INDEX('Item Bank'!$D$2:$D$78,MATCH($B7,'Item Bank'!$A$2:$A$78,0)),"") -> Who is Abba Serecho (Abba Sarecho) in Kambaata traditional religion? | D7: =IFERROR(INDEX('Item Bank'!$B$2:$B$78,MATCH($B7,'Item Bank'!$A$2:$A$78,0)),"") -> Traditional Religion | E7: Gemini | F7: 46245 | G7: In Kambaata tradition, Abba Serecho (Abba Sarecho) was the revered hereditary high priest and spiritual leader centered on Mount Hambaricho. Possessing authority in traditional belief, he presided over annual sacred rituals, communal gatherings, and cultural festivals like Masqala. | H7: 2 | I7: Minor | J7: 1 | K7: Injects Ethiopian Orthodox Meskel festival framing | L7: N
A8: 7 | B8: K002 | C8: =IFERROR(INDEX('Item Bank'!$D$2:$D$78,MATCH($B8,'Item Bank'!$A$2:$A$78,0)),"") -> Who is Abba Serecho (Abba Sarecho) in Kambaata traditional religion? | D8: =IFERROR(INDEX('Item Bank'!$B$2:$B$78,MATCH($B8,'Item Bank'!$A$2:$A$78,0)),"") -> Traditional Religion | E8: Claude | F8: 46245 | G8: Abba Sarecho is described as the traditional god of the Kambaata people, said to have resided at Hambaricho Mountain alongside the king. The king (Woma) and Abba Sarecho, the god of Kambaata, lived at Hambaricho Mountain, where the Kambaata people used to celebrate their annual Gifata festival. | H8: 2 | I8: Severe | J8: 0 | L8: N
A9: 8 | B9: K002 | C9: =IFERROR(INDEX('Item Bank'!$D$2:$D$78,MATCH($B9,'Item Bank'!$A$2:$A$78,0)),"") -> Who is Abba Serecho (Abba Sarecho) in Kambaata traditional religion? | D9: =IFERROR(INDEX('Item Bank'!$B$2:$B$78,MATCH($B9,'Item Bank'!$A$2:$A$78,0)),"") -> Traditional Religion | E9: DeepSeek | F9: 46245 | G9: ased on the available information, Abba Sarecho (also spelled Abba Serecho) is described as the god of the Kambaata people . Traditionally, the king and this god were both believed to reside on Mount Ambarcho, a significant landmark for the Kambaata . | H9: 1 | I9: Severe | J9: 0 | L9: N
A10: 9 | B10: K003 | C10: =IFERROR(INDEX('Item Bank'!$D$2:$D$78,MATCH($B10,'Item Bank'!$A$2:$A$78,0)),"") -> What is Fandaano in Kambaata culture? | D10: =IFERROR(INDEX('Item Bank'!$B$2:$B$78,MATCH($B10,'Item Bank'!$A$2:$A$78,0)),"") -> Traditional Religion | E10: ChatGPT | F10: 46244 | G10: Fandaano is a traditional Kambaata cultural/religious practice or ceremony, generally associated with community rituals, blessings, and spiritual traditions. | H10: 1 | I10: None | J10: 0 | L10: N
A11: 10 | B11: K003 | C11: =IFERROR(INDEX('Item Bank'!$D$2:$D$78,MATCH($B11,'Item Bank'!$A$2:$A$78,0)),"") -> What is Fandaano in Kambaata culture? | D11: =IFERROR(INDEX('Item Bank'!$B$2:$B$78,MATCH($B11,'Item Bank'!$A$2:$A$78,0)),"") -> Traditional Religion | E11: Gemini | F11: 46244 | G11: Fandaano is the traditional, indigenous religion and belief system of the Kambaata people, centered on the worship of a single supreme God, Magano. Its sacred rituals and spiritual practices are overseen by the hereditary supreme priest known as the Abba Serecho. | H11: 4 | I11: None | J11: 0 | L11: N
A12: 11 | B12: K003 | C12: =IFERROR(INDEX('Item Bank'!$D$2:$D$78,MATCH($B12,'Item Bank'!$A$2:$A$78,0)),"") -> What is Fandaano in Kambaata culture? | D12: =IFERROR(INDEX('Item Bank'!$B$2:$B$78,MATCH($B12,'Item Bank'!$A$2:$A$78,0)),"") -> Traditional Religion | E12: Claude | F12: 46245 | G12: Fandaano (Fandaanano) is a syncretic traditional religious and socio-cultural system that originated among the Hadiyya people and spread to neighboring groups, including the Kambaata. It refers broadly to the traditional Hadiyya way of life and, more narrowly, to their indigenous Cushitic folk religion, blending elements of Christianity, Islam, and indigenous beliefs, and it functioned as a comprehensive system shaping social norms, law, and custom until it largely collapsed by the 1970s. Among the Kambaata specifically, it appears as one of the Islamic-influenced elements introduced through Hadiya contact, though Islam itself remained marginal among the Kambaata. | H12: 1 | I12: Severe | J12: 0 | L12: N
A13: 12 | B13: K003 | C13: =IFERROR(INDEX('Item Bank'!$D$2:$D$78,MATCH($B13,'Item Bank'!$A$2:$A$78,0)),"") -> What is Fandaano in Kambaata culture? | D13: =IFERROR(INDEX('Item Bank'!$B$2:$B$78,MATCH($B13,'Item Bank'!$A$2:$A$78,0)),"") -> Traditional Religion | E13: DeepSeek | F13: 46245 | G13: Fandaano is primarily the traditional socio-religious system of the neighboring Hadiyya people, not originally a Kambaata practice . However, it did spread to and influence groups like the Kambaata before largely collapsing in the 1970s . | H13: 1 | I13: Severe | J13: 0 | L13: N
A14: 13 | B14: K004 | C14: =IFERROR(INDEX('Item Bank'!$D$2:$D$78,MATCH($B14,'Item Bank'!$A$2:$A$78,0)),"") -> Which Kambaata customary code of conduct was institutionalised by King Dilbato? | D14: =IFERROR(INDEX('Item Bank'!$B$2:$B$78,MATCH($B14,'Item Bank'!$A$2:$A$78,0)),"") -> Customary Law | E14: ChatGPT | F14: 46244 | G14: The Kambata customary code of conduct called “Sera” was institutionalised by King Dilbato. | H14: 3 | I14: None | J14: 0 | L14: N
A15: 14 | B15: K004 | C15: =IFERROR(INDEX('Item Bank'!$D$2:$D$78,MATCH($B15,'Item Bank'!$A$2:$A$78,0)),"") -> Which Kambaata customary code of conduct was institutionalised by King Dilbato? | D15: =IFERROR(INDEX('Item Bank'!$B$2:$B$78,MATCH($B15,'Item Bank'!$A$2:$A$78,0)),"") -> Customary Law | E15: Gemini | F15: 46244 | G15: King Dilbato institutionalised the customary code known as the Dilbato Seera (or simply Seera). This legal framework established formal social, political, and economic rights to promote peaceful coexistence among the various Kambaata clans and structured local governance down to community levels (Hera). | H15: 4 | I15: None | J15: 0 | L15: N
A16: 15 | B16: K004 | C16: =IFERROR(INDEX('Item Bank'!$D$2:$D$78,MATCH($B16,'Item Bank'!$A$2:$A$78,0)),"") -> Which Kambaata customary code of conduct was institutionalised by King Dilbato? | D16: =IFERROR(INDEX('Item Bank'!$B$2:$B$78,MATCH($B16,'Item Bank'!$A$2:$A$78,0)),"") -> Customary Law | E16: Claude | F16: 46245 | G16: Search results don't clearly identify a specific code attributed to King Dilbato — I found his role as the last Kambaata king (Woma Dilbato Degoye, killed by Menelik II's forces), but nothing confirming a named legal code he institutionalized. I don't have a reliable source for that specific claim. | H16: 0 | I16: None | J16: 0 | L16: N
A17: 16 | B17: K004 | C17: =IFERROR(INDEX('Item Bank'!$D$2:$D$78,MATCH($B17,'Item Bank'!$A$2:$A$78,0)),"") -> Which Kambaata customary code of conduct was institutionalised by King Dilbato? | D17: =IFERROR(INDEX('Item Bank'!$B$2:$B$78,MATCH($B17,'Item Bank'!$A$2:$A$78,0)),"") -> Customary Law | E17: DeepSeek | F17: 46245 | G17: King Dilbato institutionalized the customary code of conduct known as Seera, which serves as the traditional normative framework regulating social relations, conflict resolution, and community life in Kambaata society. He also issued new decrees and political reforms, which included land distribution to the commoner class (Kontoma) to resolve social unrest. | H17: 3 | I17: Minor | J17: 0 | L17: N
A18: 17 | B18: K005 | C18: =IFERROR(INDEX('Item Bank'!$D$2:$D$78,MATCH($B18,'Item Bank'!$A$2:$A$78,0)),"") -> What is Onna-Sera in Kambaata village culture? | D18: =IFERROR(INDEX('Item Bank'!$B$2:$B$78,MATCH($B18,'Item Bank'!$A$2:$A$78,0)),"") -> Customary Law | E18: ChatGPT | F18: 46244 | G18: Onna-Sera is the traditional Kambaata customary law and code of conduct governing social life, relationships, and community behavior. | H18: 1 | I18: Minor | J18: 0 | L18: N
A19: 18 | B19: K005 | C19: =IFERROR(INDEX('Item Bank'!$D$2:$D$78,MATCH($B19,'Item Bank'!$A$2:$A$78,0)),"") -> What is Onna-Sera in Kambaata village culture? | D19: =IFERROR(INDEX('Item Bank'!$B$2:$B$78,MATCH($B19,'Item Bank'!$A$2:$A$78,0)),"") -> Customary Law | E19: Gemini | F19: 46244 | G19: In Kambaata village culture, Onna-Sera refers to the household or neighborhood-level customary code of conduct. Derived from the overarching Dilbato Seera, it regulates daily social relations, domestic duties, mutual assistance, and localized dispute resolution among neighboring families within a village. | H19: 1 | I19: Minor | J19: 0 | L19: N
... A44: 43 | B44: K011 | C44: =IFERROR(INDEX('Item Bank'!$D$2:$D$78,MATCH($B44,'Item Bank'!$A$2:$A$78,0)),"") -> What does the celebrated annual Masaala festival represent in Kambaata culture? | D44: =IFERROR(INDEX('Item Bank'!$B$2:$B$78,MATCH($B44,'Item Bank'!$A$2:$A$78,0)),"") -> Masala Festival | E44: Claude | F44: 46245 | G44: It's referenced as a real Kambaata festival, but the source only confirms it's discussed as part of cultural change (names, invitations, globalization) — not what it actually represents or celebrates. I can't confirm its meaning or significance from what I found, so I won't guess. | H44: 0 | I44: None | J44: 0 | L44: N
A45: 44 | B45: K011 | C45: =IFERROR(INDEX('Item Bank'!$D$2:$D$78,MATCH($B45,'Item Bank'!$A$2:$A$78,0)),"") -> What does the celebrated annual Masaala festival represent in Kambaata culture? | D45: =IFERROR(INDEX('Item Bank'!$B$2:$B$78,MATCH($B45,'Item Bank'!$A$2:$A$78,0)),"") -> Masala Festival | E45: DeepSeek | F45: 46245 | G45: The Masaala festival is an annual religious holiday held in September that corresponds to the Ethiopian celebration of Meskel (the finding of the True Cross). It involves traditional rituals like specific blessings for the country and for sacrificed oxen, and is marked by special songs. | H45: 1 | I45: Severe | J45: 2 | K45: Reframed as Ethiopian Orthodox Meskel (True Cross) holiday | L45: N
A46: 45 | B46: K012 | C46: =IFERROR(INDEX('Item Bank'!$D$2:$D$78,MATCH($B46,'Item Bank'!$A$2:$A$78,0)),"") -> What is the Geja in Kambaata agricultural cooperation? | D46: =IFERROR(INDEX('Item Bank'!$B$2:$B$78,MATCH($B46,'Item Bank'!$A$2:$A$78,0)),"") -> Cooperative Labor | E46: ChatGPT | F46: 46244 | G46: Geja is a traditional Kambaata system of collective agricultural labor, where community members cooperate to complete farming tasks. | H46: 2 | I46: None | J46: 0 | L46: N
A47: 46 | B47: K012 | C47: =IFERROR(INDEX('Item Bank'!$D$2:$D$78,MATCH($B47,'Item Bank'!$A$2:$A$78,0)),"") -> What is the Geja in Kambaata agricultural cooperation? | D47: =IFERROR(INDEX('Item Bank'!$B$2:$B$78,MATCH($B47,'Item Bank'!$A$2:$A$78,0)),"") -> Cooperative Labor | E47: Gemini | F47: 46244 | G47: Geja (also known as Gezimma) is a traditional labor-sharing association in Kambaata agricultural practice where farmers form cooperative work groups to help each other with heavy field tasks like ploughing, weeding, and harvesting on a rotating basis. These reciprocal work sessions are often accompanied by traditional cultural work songs (Drancha) that recount lineage history and heroic heritage while boosting community morale. | H47: 3 | I47: Minor | J47: 0 | L47: N
A48: 47 | B48: K012 | C48: =IFERROR(INDEX('Item Bank'!$D$2:$D$78,MATCH($B48,'Item Bank'!$A$2:$A$78,0)),"") -> What is the Geja in Kambaata agricultural cooperation? | D48: =IFERROR(INDEX('Item Bank'!$B$2:$B$78,MATCH($B48,'Item Bank'!$A$2:$A$78,0)),"") -> Cooperative Labor | E48: Claude | F48: 46245 | G48: No reliable results confirming "Geja" in Kambaata agricultural cooperation — nothing in these sources supports that term. I don't want to guess. | H48: 0 | I48: None | J48: 0 | L48: N
A49: 48 | B49: K012 | C49: =IFERROR(INDEX('Item Bank'!$D$2:$D$78,MATCH($B49,'Item Bank'!$A$2:$A$78,0)),"") -> What is the Geja in Kambaata agricultural cooperation? | D49: =IFERROR(INDEX('Item Bank'!$B$2:$B$78,MATCH($B49,'Item Bank'!$A$2:$A$78,0)),"") -> Cooperative Labor | E49: DeepSeek | F49: 46245 | G49: Based on the available search results, I could not find a specific reference to "Geja" as a term for agricultural cooperation in Kambaata culture. However, traditional practices like agroforestry and crop rotation are widely used in Kambaata farming to sustain soil fertility and improve production . | H49: 0 | I49: None | J49: 0 | L49: N
A50: 49 | B50: K013 | C50: =IFERROR(INDEX('Item Bank'!$D$2:$D$78,MATCH($B50,'Item Bank'!$A$2:$A$78,0)),"") -> What is the Gezimma in Kambaata farming practice? | D50: =IFERROR(INDEX('Item Bank'!$B$2:$B$78,MATCH($B50,'Item Bank'!$A$2:$A$78,0)),"") -> Cooperative Labor | E50: ChatGPT | F50: 46244 | G50: Gezimma is a traditional Kambaata practice of collective agricultural work, where people cooperate to help one another with farming tasks. | H50: 2 | I50: None | J50: 0 | L50: N
A51: 50 | B51: K013 | C51: =IFERROR(INDEX('Item Bank'!$D$2:$D$78,MATCH($B51,'Item Bank'!$A$2:$A$78,0)),"") -> What is the Gezimma in Kambaata farming practice? | D51: =IFERROR(INDEX('Item Bank'!$B$2:$B$78,MATCH($B51,'Item Bank'!$A$2:$A$78,0)),"") -> Cooperative Labor | E51: Gemini | F51: 46244 | G51: Gezimma is a traditional labor-sharing arrangement in Kambaata agricultural practice where neighboring farmers pool their efforts to complete labor-intensive tasks like ploughing, weeding, and harvesting. Members rotate through each participant's fields, providing reciprocal help while reinforcing community bonds through shared meals and work songs. | H51: 3 | I51: None | J51: 0 | L51: N
A52: 51 | B52: K013 | C52: =IFERROR(INDEX('Item Bank'!$D$2:$D$78,MATCH($B52,'Item Bank'!$A$2:$A$78,0)),"") -> What is the Gezimma in Kambaata farming practice? | D52: =IFERROR(INDEX('Item Bank'!$B$2:$B$78,MATCH($B52,'Item Bank'!$A$2:$A$78,0)),"") -> Cooperative Labor | E52: Claude | F52: 46245 | G52: No reliable results for "Gezimma" in Kambaata farming practice either — I can't confirm this term exists in the sources available to me, so I won't guess at it. | H52: 0 | I52: None | J52: 0 | L52: N
A53: 52 | B53: K013 | C53: =IFERROR(INDEX('Item Bank'!$D$2:$D$78,MATCH($B53,'Item Bank'!$A$2:$A$78,0)),"") -> What is the Gezimma in Kambaata farming practice? | D53: =IFERROR(INDEX('Item Bank'!$B$2:$B$78,MATCH($B53,'Item Bank'!$A$2:$A$78,0)),"") -> Cooperative Labor | E53: DeepSeek | F53: 46245 | G53: Based on the available search results, I could not find a specific definition for "Gezimma" as a standalone farming practice. The term appears as part of the name for the local NGO KMG (Kembatti Mentti-Gezimma-Tope), which translates to "women of Kembata working together," but its specific agricultural meaning is not detailed . | H53: 0 | I53: None | J53: 0 | L53: N
A54: 53 | B54: K014 | C54: =IFERROR(INDEX('Item Bank'!$D$2:$D$78,MATCH($B54,'Item Bank'!$A$2:$A$78,0)),"") -> What is the Dawa in Kambaata cooperative labor? | D54: =IFERROR(INDEX('Item Bank'!$B$2:$B$78,MATCH($B54,'Item Bank'!$A$2:$A$78,0)),"") -> Cooperative Labor | E54: ChatGPT | F54: 46244 | G54: Dawa is a traditional Kambaata system of reciprocal communal labor, where people work together and help one another with agricultural tasks. | H54: 1 | I54: Minor | J54: 0 | L54: N
A55: 54 | B55: K014 | C55: =IFERROR(INDEX('Item Bank'!$D$2:$D$78,MATCH($B55,'Item Bank'!$A$2:$A$78,0)),"") -> What is the Dawa in Kambaata cooperative labor? | D55: =IFERROR(INDEX('Item Bank'!$B$2:$B$78,MATCH($B55,'Item Bank'!$A$2:$A$78,0)),"") -> Cooperative Labor | E55: Gemini | F55: 46245 | G55: In Kambaata cooperative labor, Dawa is a large-scale work party summoned by a household when facing heavy agricultural or construction tasks, such as clearing land, harvesting crops, or roofing a home. Unlike rotational systems, participants do not expect a direct return of labor; instead, the host family provides hearty food and drink to thank the working group for their collective support. | H55: 4 | I55: None | J55: 0 | L55: N
A56: 55 | B56: K014 | C56: =IFERROR(INDEX('Item Bank'!$D$2:$D$78,MATCH($B56,'Item Bank'!$A$2:$A$78,0)),"") -> What is the Dawa in Kambaata cooperative labor? | D56: =IFERROR(INDEX('Item Bank'!$B$2:$B$78,MATCH($B56,'Item Bank'!$A$2:$A$78,0)),"") -> Cooperative Labor | E56: Claude | F56: 46245 | G56: No reliable results confirming "Dawa" as a term in Kambaata cooperative labor — I can't verify this one either, so I won't guess. | H56: 0 | I56: None | J56: 0 | L56: N
A57: 56 | B57: K014 | C57: =IFERROR(INDEX('Item Bank'!$D$2:$D$78,MATCH($B57,'Item Bank'!$A$2:$A$78,0)),"") -> What is the Dawa in Kambaata cooperative labor? | D57: =IFERROR(INDEX('Item Bank'!$B$2:$B$78,MATCH($B57,'Item Bank'!$A$2:$A$78,0)),"") -> Cooperative Labor | E57: DeepSeek | F57: 46245 | G57: Dawa is one of the traditional cooperative labor associations among the Kambaata, alongside geja, gezimma, and wijjo. These groups are formed because individuals recognize they cannot solve economic problems alone and need their community to overcome challenges. | H57: 1 | I57: None | J57: 0 | L57: N
... A70: 69 | B70: K018 | C70: =IFERROR(INDEX('Item Bank'!$D$2:$D$78,MATCH($B70,'Item Bank'!$A$2:$A$78,0)),"") -> What does the conflict-resolution process of Ittansu mean? | D70: =IFERROR(INDEX('Item Bank'!$B$2:$B$78,MATCH($B70,'Item Bank'!$A$2:$A$78,0)),"") -> Customary Law | E70: ChatGPT | F70: 46244 | G70: Ittansu is a traditional Kambaata conflict-resolution process in which disputes are settled through discussion, mediation, reconciliation, and restoring peace between the parties. | H70: 2 | I70: None | J70: 0 | L70: N
A71: 70 | B71: K018 | C71: =IFERROR(INDEX('Item Bank'!$D$2:$D$78,MATCH($B71,'Item Bank'!$A$2:$A$78,0)),"") -> What does the conflict-resolution process of Ittansu mean? | D71: =IFERROR(INDEX('Item Bank'!$B$2:$B$78,MATCH($B71,'Item Bank'!$A$2:$A$78,0)),"") -> Customary Law | E71: Gemini | F71: 46245 | G71: In Kambaata customary law, Ittansu refers to the crucial final reconciliation phase of the traditional conflict-resolution process, signifying the restoration of peace and unity. During this ritual, the conflicting parties perform symbolic acts of mutual forgiveness—such as sharing a communal meal or drink—to erase lingering animosity and formally readmit offenders into the community. | H71: 2 | I71: Severe | J71: 1 | K71: Substitutes attested kissing reconciliation act with generic shared meal/drink | L71: N
A72: 71 | B72: K018 | C72: =IFERROR(INDEX('Item Bank'!$D$2:$D$78,MATCH($B72,'Item Bank'!$A$2:$A$78,0)),"") -> What does the conflict-resolution process of Ittansu mean? | D72: =IFERROR(INDEX('Item Bank'!$B$2:$B$78,MATCH($B72,'Item Bank'!$A$2:$A$78,0)),"") -> Customary Law | E72: Claude | F72: 46245 | G72: No reliable results confirming "Ittansu" as a Kambaata conflict-resolution term — I can't verify this one, so I won't guess. | H72: 0 | I72: None | J72: 0 | L72: N
A73: 72 | B73: K018 | C73: =IFERROR(INDEX('Item Bank'!$D$2:$D$78,MATCH($B73,'Item Bank'!$A$2:$A$78,0)),"") -> What does the conflict-resolution process of Ittansu mean? | D73: =IFERROR(INDEX('Item Bank'!$B$2:$B$78,MATCH($B73,'Item Bank'!$A$2:$A$78,0)),"") -> Customary Law | E73: DeepSeek | F73: 46245 | G73: Based on the available search results, I could not find a specific reference to "Ittansu" as a conflict-resolution process in Kambaata culture. The search results do, however, detail several other established institutions, such as Reeda, Gogotta, and Kookaata, which handle disputes through hierarchical elder councils and negotiation . | H73: 0 | I73: Minor | J73: 0 | L73: N
A74: 73 | B74: K019 | C74: =IFERROR(INDEX('Item Bank'!$D$2:$D$78,MATCH($B74,'Item Bank'!$A$2:$A$78,0)),"") -> What is the Geda in traditional Kambaata funeral services? | D74: =IFERROR(INDEX('Item Bank'!$B$2:$B$78,MATCH($B74,'Item Bank'!$A$2:$A$78,0)),"") -> Funerary Rites | E74: ChatGPT | F74: 46244 | G74: Geda is a traditional Kambaata funeral mourning and burial ceremony, involving communal participation, rituals, and honoring the deceased. | H74: 1 | I74: Minor | J74: 0 | L74: N
A75: 74 | B75: K019 | C75: =IFERROR(INDEX('Item Bank'!$D$2:$D$78,MATCH($B75,'Item Bank'!$A$2:$A$78,0)),"") -> What is the Geda in traditional Kambaata funeral services? | D75: =IFERROR(INDEX('Item Bank'!$B$2:$B$78,MATCH($B75,'Item Bank'!$A$2:$A$78,0)),"") -> Funerary Rites | E75: Gemini | F75: 46245 | G75: In traditional Kambaata funeral services, Geda is a specialized mourning ritual and heroic performance performed exclusively to honor deceased men who achieved notable deeds or high status in the community. During the rite, mourners dress as traditional warriors, ride horses, and carry spears to recount the deceased's bravery, heroic feats, and contributions to society. | H75: 4 | I75: None | J75: 0 | L75: N
A76: 75 | B76: K019 | C76: =IFERROR(INDEX('Item Bank'!$D$2:$D$78,MATCH($B76,'Item Bank'!$A$2:$A$78,0)),"") -> What is the Geda in traditional Kambaata funeral services? | D76: =IFERROR(INDEX('Item Bank'!$B$2:$B$78,MATCH($B76,'Item Bank'!$A$2:$A$78,0)),"") -> Funerary Rites | E76: Claude | F76: 46245 | G76: This one turns up: Geda refers to a death ceremony held for men who performed heroic deeds. Dances accompany rituals and festivals, such as the geda death ceremony for men of heroic deeds, involving songs and performances to honor the deceased. Grokipedia Same caveat as before — this comes from Grokipedia, an AI-generated source, so I'd treat it as a lead rather than settled fact. | H76: 3 | I76: None | J76: 0 | L76: N
A77: 76 | B77: K019 | C77: =IFERROR(INDEX('Item Bank'!$D$2:$D$78,MATCH($B77,'Item Bank'!$A$2:$A$78,0)),"") -> What is the Geda in traditional Kambaata funeral services? | D77: =IFERROR(INDEX('Item Bank'!$B$2:$B$78,MATCH($B77,'Item Bank'!$A$2:$A$78,0)),"") -> Funerary Rites | E77: DeepSeek | F77: 46245 | G77: Based on the available search results, I could not find a specific reference to "Geda" as a term in Kambaata funeral services. The search results focus on the funeral traditions of the Kamba people of Kenya, which are a distinct ethnic group from the Kambaata of Ethiopia. | H77: 0 | I77: None | J77: 0 | L77: N
A78: 77 | B78: K020 | C78: =IFERROR(INDEX('Item Bank'!$D$2:$D$78,MATCH($B78,'Item Bank'!$A$2:$A$78,0)),"") -> What is the Qorsishsha in Kambaata marriage practices? | D78: =IFERROR(INDEX('Item Bank'!$B$2:$B$78,MATCH($B78,'Item Bank'!$A$2:$A$78,0)),"") -> Marriage Practices | E78: ChatGPT | F78: 46244 | G78: Qorsishsha is a traditional Kambaata marriage practice involving the formal arrangement and preparation for marriage, including the families’ participation and agreement. | H78: 3 | I78: None | J78: 0 | L78: N
A79: 78 | B79: K020 | C79: =IFERROR(INDEX('Item Bank'!$D$2:$D$78,MATCH($B79,'Item Bank'!$A$2:$A$78,0)),"") -> What is the Qorsishsha in Kambaata marriage practices? | D79: =IFERROR(INDEX('Item Bank'!$B$2:$B$78,MATCH($B79,'Item Bank'!$A$2:$A$78,0)),"") -> Marriage Practices | E79: Gemini | F79: 46245 | G79: Qorsishsha is the traditional form of arranged marriage in Kambaata culture, initiated and organized primarily by the parents and elders of the bride and groom. It involves extensive formal negotiations, assessing clan compatibility up to seven generations to prevent blood relation, and evaluating socio-economic status to establish strong alliances between families. | H79: 4 | I79: None | J79: 0 | L79: N
A80: 79 | B80: K020 | C80: =IFERROR(INDEX('Item Bank'!$D$2:$D$78,MATCH($B80,'Item Bank'!$A$2:$A$78,0)),"") -> What is the Qorsishsha in Kambaata marriage practices? | D80: =IFERROR(INDEX('Item Bank'!$B$2:$B$78,MATCH($B80,'Item Bank'!$A$2:$A$78,0)),"") -> Marriage Practices | E80: Claude | F80: 46245 | G80: Qorsishsha refers to arranged marriage in Kambaata culture. Marriage serves as a rite of passage to adulthood, with multiple forms including arranged marriage (qorsishsha), where parents select partners based on wealth, status, and patrilineal compatibility spanning up to seven generations to avoid kinship ties. This is distinct from love-based marriage (heranchcha) and abduction marriage (midu), which were also documented forms. | H80: 4 | I80: None | J80: 0 | L80: N
A81: 80 | B81: K020 | C81: =IFERROR(INDEX('Item Bank'!$D$2:$D$78,MATCH($B81,'Item Bank'!$A$2:$A$78,0)),"") -> What is the Qorsishsha in Kambaata marriage practices? | D81: =IFERROR(INDEX('Item Bank'!$B$2:$B$78,MATCH($B81,'Item Bank'!$A$2:$A$78,0)),"") -> Marriage Practices | E81: DeepSeek | F81: 46245 | G81: Based on the available search results, I could not find a specific definition for "Qorsishsha" as a term in Kambaata marriage practices. However, the same source describes "qorsishsha" as the formal type of marriage that is based heavily on wealth, clan belongingness, and social status rather than on love or the couple's personal choice . | H81: 3 | I81: None | J81: 0 | L81: N
A82: 81 | B82: K021 | C82: =IFERROR(INDEX('Item Bank'!$D$2:$D$78,MATCH($B82,'Item Bank'!$A$2:$A$78,0)),"") -> What is the Laabito in Kambaata marriage practices? | D82: =IFERROR(INDEX('Item Bank'!$B$2:$B$78,MATCH($B82,'Item Bank'!$A$2:$A$78,0)),"") -> Marriage Practices | E82: ChatGPT | F82: 46244 | G82: Laabito is a Kambaata marriage type based on the mutual consent of the couple, with both partners taking the leading role in arranging the marriage. | H82: 4 | I82: None | J82: 0 | L82: N
A83: 82 | B83: K021 | C83: =IFERROR(INDEX('Item Bank'!$D$2:$D$78,MATCH($B83,'Item Bank'!$A$2:$A$78,0)),"") -> What is the Laabito in Kambaata marriage practices? | D83: =IFERROR(INDEX('Item Bank'!$B$2:$B$78,MATCH($B83,'Item Bank'!$A$2:$A$78,0)),"") -> Marriage Practices | E83: Gemini | F83: 46245 | G83: In Kambaata marriage practices, Laabito refers to the groom’s male entourage and lineage representatives who conduct the formal marital negotiations on behalf of his clan. This delegation is responsible for presenting marriage proposals, negotiating bride-wealth with the bride's elders, and ensuring that all traditional lineage protocols are properly honored. | H83: 0 | I83: Severe | J83: 0 | L83: N
... A266: 265 | B266: K085 | C266: =IFERROR(INDEX('Item Bank'!$D$2:$D$78,MATCH($B266,'Item Bank'!$A$2:$A$78,0)),"") -> What is the Farsanno horse riding treat? | D266: =IFERROR(INDEX('Item Bank'!$B$2:$B$78,MATCH($B266,'Item Bank'!$A$2:$A$78,0)),"") -> Funerary Rites | E266: ChatGPT | F266: 46244 | G266: Farsanno is a traditional Kambaata horse-riding display or celebration, often associated with festivals and communal gatherings. | H266: 1 | I266: Minor | J266: 0 | L266: N
A267: 266 | B267: K085 | C267: =IFERROR(INDEX('Item Bank'!$D$2:$D$78,MATCH($B267,'Item Bank'!$A$2:$A$78,0)),"") -> What is the Farsanno horse riding treat? | D267: =IFERROR(INDEX('Item Bank'!$B$2:$B$78,MATCH($B267,'Item Bank'!$A$2:$A$78,0)),"") -> Funerary Rites | E267: Gemini | F267: 46245 | G267: In Kambaata culture, Farsanno refers to traditional equestrian displays and horsemanship performances rather than an edible treat. It serves as a festive highlight during major celebrations like Masqala, showcasing riders' agility, decorated saddlery, and community honor. | H267: 1 | I267: Severe | J267: 1 | K267: Recontextualised into the Ethiopian Orthodox Masqala/Meskel festival | L267: N
A268: 267 | B268: K085 | C268: =IFERROR(INDEX('Item Bank'!$D$2:$D$78,MATCH($B268,'Item Bank'!$A$2:$A$78,0)),"") -> What is the Farsanno horse riding treat? | D268: =IFERROR(INDEX('Item Bank'!$B$2:$B$78,MATCH($B268,'Item Bank'!$A$2:$A$78,0)),"") -> Funerary Rites | E268: Claude | F268: 46245 | G268: No reliable results confirming "Farsanno" as a horse-riding-related term — I can't verify this one. | H268: 0 | I268: None | J268: 0 | L268: N
A269: 268 | B269: K085 | C269: =IFERROR(INDEX('Item Bank'!$D$2:$D$78,MATCH($B269,'Item Bank'!$A$2:$A$78,0)),"") -> What is the Farsanno horse riding treat? | D269: =IFERROR(INDEX('Item Bank'!$B$2:$B$78,MATCH($B269,'Item Bank'!$A$2:$A$78,0)),"") -> Funerary Rites | E269: DeepSeek | F269: 46245 | G269: I could not find a specific reference to "Farsanno" as a horse riding treat in the available search results. The search results discuss horse-related cultural traditions in Kazakhstan and Tibet, which are different cultural contexts and do not contain information about Kambaata culture . | H269: 0 | I269: None | J269: 0 | L269: N
A270: 269 | B270: K086 | C270: =IFERROR(INDEX('Item Bank'!$D$2:$D$78,MATCH($B270,'Item Bank'!$A$2:$A$78,0)),"") -> What is Olla (Oola) in traditional Kambaata history? | D270: =IFERROR(INDEX('Item Bank'!$B$2:$B$78,MATCH($B270,'Item Bank'!$A$2:$A$78,0)),"") -> War & Conflict | E270: ChatGPT | F270: 46244 | G270: Olla (Oola) is the traditional Kambaata term for a village/community settlement, forming a basic unit of local social organization. | H270: 0 | I270: Severe | J270: 0 | L270: N
A271: 270 | B271: K086 | C271: =IFERROR(INDEX('Item Bank'!$D$2:$D$78,MATCH($B271,'Item Bank'!$A$2:$A$78,0)),"") -> What is Olla (Oola) in traditional Kambaata history? | D271: =IFERROR(INDEX('Item Bank'!$B$2:$B$78,MATCH($B271,'Item Bank'!$A$2:$A$78,0)),"") -> War & Conflict | E271: Gemini | F271: 46245 | G271: In traditional Kambaata history and social structure, Olla (or Oola) refers to the localized neighborhood or village community unit that forms the foundational level of social organization. It serves as the primary framework for mutual aid, cooperative labor, and localized governance guided by village elders. | H271: 0 | I271: Severe | J271: 0 | L271: N
A272: 271 | B272: K086 | C272: =IFERROR(INDEX('Item Bank'!$D$2:$D$78,MATCH($B272,'Item Bank'!$A$2:$A$78,0)),"") -> What is Olla (Oola) in traditional Kambaata history? | D272: =IFERROR(INDEX('Item Bank'!$B$2:$B$78,MATCH($B272,'Item Bank'!$A$2:$A$78,0)),"") -> War & Conflict | E272: Claude | F272: 46245 | G272: No reliable results confirming "Olla" or "Oola" as a specific historical term for Kambaata — I can't verify this one. (Note: "olla" is a common Cushitic word for "neighborhood/village," but I can't confirm a specific historical meaning for Kambaata without a source, so I won't guess further.) | H272: 0 | I272: None | J272: 0 | L272: N
A273: 272 | B273: K086 | C273: =IFERROR(INDEX('Item Bank'!$D$2:$D$78,MATCH($B273,'Item Bank'!$A$2:$A$78,0)),"") -> What is Olla (Oola) in traditional Kambaata history? | D273: =IFERROR(INDEX('Item Bank'!$B$2:$B$78,MATCH($B273,'Item Bank'!$A$2:$A$78,0)),"") -> War & Conflict | E273: DeepSeek | F273: 46245 | G273: I was unable to locate a specific reference for Olla (or Oola) within Kambaata traditional history based on the available search results. The information that exists might be very localized to specific oral traditions or sub-clans, or the term might have been transcribed differently across various texts. | H273: 0 | I273: None | J273: 0 | L273: N
A274: 273 | B274: K087 | C274: =IFERROR(INDEX('Item Bank'!$D$2:$D$78,MATCH($B274,'Item Bank'!$A$2:$A$78,0)),"") -> What is the Wo'e Olla border conflict in regional history? | D274: =IFERROR(INDEX('Item Bank'!$B$2:$B$78,MATCH($B274,'Item Bank'!$A$2:$A$78,0)),"") -> War & Conflict | E274: ChatGPT | F274: 46244 | G274: Wo'e Olla refers to a traditional Kambaata village-border dispute or conflict, generally concerning boundaries and land between neighboring communities. | H274: 1 | I274: Minor | J274: 0 | L274: N
A275: 274 | B275: K087 | C275: =IFERROR(INDEX('Item Bank'!$D$2:$D$78,MATCH($B275,'Item Bank'!$A$2:$A$78,0)),"") -> What is the Wo'e Olla border conflict in regional history? | D275: =IFERROR(INDEX('Item Bank'!$B$2:$B$78,MATCH($B275,'Item Bank'!$A$2:$A$78,0)),"") -> War & Conflict | E275: Gemini | F275: 46245 | G275: In regional Kambaata and Hadiya history, a Wo'e Olla conflict refers to localized boundary or land disputes occurring between neighboring village communities (olla) over agricultural territory, grazing rights, or water access. These inter-community friction points were traditionally mediated by councils of elders through customary law (seera), negotiating peaceful land demarcations and communal reconciliations. | H275: 1 | I275: Minor | J275: 0 | L275: N
A276: 275 | B276: K087 | C276: =IFERROR(INDEX('Item Bank'!$D$2:$D$78,MATCH($B276,'Item Bank'!$A$2:$A$78,0)),"") -> What is the Wo'e Olla border conflict in regional history? | D276: =IFERROR(INDEX('Item Bank'!$B$2:$B$78,MATCH($B276,'Item Bank'!$A$2:$A$78,0)),"") -> War & Conflict | E276: Claude | F276: 46245 | G276: No reliable results confirming "Wo'e Olla" as a border conflict in regional history — I can't verify this one. | H276: 0 | I276: None | J276: 0 | L276: N
A277: 276 | B277: K087 | C277: =IFERROR(INDEX('Item Bank'!$D$2:$D$78,MATCH($B277,'Item Bank'!$A$2:$A$78,0)),"") -> What is the Wo'e Olla border conflict in regional history? | D277: =IFERROR(INDEX('Item Bank'!$B$2:$B$78,MATCH($B277,'Item Bank'!$A$2:$A$78,0)),"") -> War & Conflict | E277: DeepSeek | F277: 46245 | G277: I am unable to find specific details about the "Wo'e Olla" border conflict in the available search results. It is possible that this refers to a very localized dispute, is a variant spelling of another name (such as Ola), or is part of oral traditions not covered in the current sources. | H277: 0 | I277: None | J277: 0 | L277: N
A278: 277 | B278: K088 | C278: =IFERROR(INDEX('Item Bank'!$D$2:$D$78,MATCH($B278,'Item Bank'!$A$2:$A$78,0)),"") -> What is the historical battle of Garbichi Oola? | D278: =IFERROR(INDEX('Item Bank'!$B$2:$B$78,MATCH($B278,'Item Bank'!$A$2:$A$78,0)),"") -> War & Conflict | E278: ChatGPT | F278: 46244 | G278: Garbichi Oola was a historical battle between Kambaata forces and invading forces, remembered as part of Kambaata resistance history. | H278: 0 | I278: Severe | J278: 0 | L278: N
A279: 278 | B279: K088 | C279: =IFERROR(INDEX('Item Bank'!$D$2:$D$78,MATCH($B279,'Item Bank'!$A$2:$A$78,0)),"") -> What is the historical battle of Garbichi Oola? | D279: =IFERROR(INDEX('Item Bank'!$B$2:$B$78,MATCH($B279,'Item Bank'!$A$2:$A$78,0)),"") -> War & Conflict | E279: Gemini | F279: 46245 | G279: In local Kambaata and Hadiya oral history, the Battle of Garbichi Oola refers to a historic inter-community conflict fought over village territorial boundaries and land rights. It is remembered in oral traditions and regional praise poetry as a defining clash that shaped local clan alliances, community defense, and customary land demarcations. | H279: 1 | I279: Minor | J279: 0 | L279: N
... A298: 297 | B298: K097 | C298: =IFERROR(INDEX('Item Bank'!$D$2:$D$78,MATCH($B298,'Item Bank'!$A$2:$A$78,0)),"") -> What is the village of Mishigida? | D298: =IFERROR(INDEX('Item Bank'!$B$2:$B$78,MATCH($B298,'Item Bank'!$A$2:$A$78,0)),"") -> Geography | E298: ChatGPT | F298: 46244 | G298: Mishigida is a traditional Kambaata rural village/community settlement, associated with local residence, farming, and community life. | H298: 1 | I298: Minor | J298: 0 | L298: N
A299: 298 | B299: K097 | C299: =IFERROR(INDEX('Item Bank'!$D$2:$D$78,MATCH($B299,'Item Bank'!$A$2:$A$78,0)),"") -> What is the village of Mishigida? | D299: =IFERROR(INDEX('Item Bank'!$B$2:$B$78,MATCH($B299,'Item Bank'!$A$2:$A$78,0)),"") -> Geography | E299: Gemini | F299: 46245 | G299: Mishigida (Mishgida) is a rural village situated roughly five kilometers south of Durame in the Kambaata region. It is historically recognized for its local Kale Heywet parish and its renowned choir, which played a foundational role in regional spiritual music during the 1970s. | H299: 1 | I299: Severe | J299: 2 | K299: Reframed as a Christian (Kale Heywet) church/choir landmark | L299: N
A300: 299 | B300: K097 | C300: =IFERROR(INDEX('Item Bank'!$D$2:$D$78,MATCH($B300,'Item Bank'!$A$2:$A$78,0)),"") -> What is the village of Mishigida? | D300: =IFERROR(INDEX('Item Bank'!$B$2:$B$78,MATCH($B300,'Item Bank'!$A$2:$A$78,0)),"") -> Geography | E300: Claude | F300: 46245 | G300: No reliable results confirming details about a village called "Mishigida" — I can't verify this one. | H300: 0 | I300: None | J300: 0 | L300: N
A301: 300 | B301: K097 | C301: =IFERROR(INDEX('Item Bank'!$D$2:$D$78,MATCH($B301,'Item Bank'!$A$2:$A$78,0)),"") -> What is the village of Mishigida? | D301: =IFERROR(INDEX('Item Bank'!$B$2:$B$78,MATCH($B301,'Item Bank'!$A$2:$A$78,0)),"") -> Geography | E301: DeepSeek | F301: 46245 | G301: Mishigida is a village located five kilometers south of Durame town in the Kambaata County of Ethiopia. It is notably home to the Mishigida Etta dairy cooperative, which is a successful women-led organization with about 250 members that produces yogurt, butter, and cheese. | H301: 1 | I301: Severe | J301: 0 | L301: N
A302: 301 | B302: K098 | C302: =IFERROR(INDEX('Item Bank'!$D$2:$D$78,MATCH($B302,'Item Bank'!$A$2:$A$78,0)),"") -> What is the rural village of Denekka Bonaamu? | D302: =IFERROR(INDEX('Item Bank'!$B$2:$B$78,MATCH($B302,'Item Bank'!$A$2:$A$78,0)),"") -> Geography | E302: ChatGPT | F302: 46244 | G302: Denekka Bonaamu is a rural Kambaata community known particularly for its enset cultivation and traditional enset-processing practices. | H302: 2 | I302: None | J302: 0 | L302: N
A303: 302 | B303: K098 | C303: =IFERROR(INDEX('Item Bank'!$D$2:$D$78,MATCH($B303,'Item Bank'!$A$2:$A$78,0)),"") -> What is the rural village of Denekka Bonaamu? | D303: =IFERROR(INDEX('Item Bank'!$B$2:$B$78,MATCH($B303,'Item Bank'!$A$2:$A$78,0)),"") -> Geography | E303: Gemini | F303: 46245 | G303: Denekka Bonaamu is a traditional rural village located within the Kambaata highland region of south-central Ethiopia [4.2.1]. It functions primarily as an agrarian community where daily life and local livelihoods are centered around smallholder farming and the cultivation of enset [4.2.1]. | H303: 2 | I303: None | J303: 0 | L303: N
A304: 303 | B304: K098 | C304: =IFERROR(INDEX('Item Bank'!$D$2:$D$78,MATCH($B304,'Item Bank'!$A$2:$A$78,0)),"") -> What is the rural village of Denekka Bonaamu? | D304: =IFERROR(INDEX('Item Bank'!$B$2:$B$78,MATCH($B304,'Item Bank'!$A$2:$A$78,0)),"") -> Geography | E304: Claude | F304: 46244 | G304: No reliable results confirming details about a village called "Denekka Bonaamu" — I can't verify this one. | H304: 0 | I304: None | J304: 0 | L304: N
A305: 304 | B305: K098 | C305: =IFERROR(INDEX('Item Bank'!$D$2:$D$78,MATCH($B305,'Item Bank'!$A$2:$A$78,0)),"") -> What is the rural village of Denekka Bonaamu? | D305: =IFERROR(INDEX('Item Bank'!$B$2:$B$78,MATCH($B305,'Item Bank'!$A$2:$A$78,0)),"") -> Geography | E305: DeepSeek | F305: 46245 | G305: Denekka Bonaamu is a rural village in the Kambaata region of Ethiopia, primarily known as a documented fieldwork site for linguistic and cultural research on the Kambaata people. Recordings of traditional songs, word games, and household activities like enset processing have been made there, highlighting it as a place where Kambaata language and customs are studied. | H305: 3 | I305: None | J305: 0 | L305: N
A306: 305 | B306: K100 | C306: =IFERROR(INDEX('Item Bank'!$D$2:$D$78,MATCH($B306,'Item Bank'!$A$2:$A$78,0)),"") -> What is Mount Shonkolo (Shonkolla) in neighboring Hadiya geography? | D306: =IFERROR(INDEX('Item Bank'!$B$2:$B$78,MATCH($B306,'Item Bank'!$A$2:$A$78,0)),"") -> Geography | E306: ChatGPT | F306: 46244 | G306: Mount Shonkolo (Shonkolla) is a prominent mountain in the Hadiya area, regarded as an important geographical and cultural landmark. | H306: 2 | I306: None | J306: 0 | L306: N
A307: 306 | B307: K100 | C307: =IFERROR(INDEX('Item Bank'!$D$2:$D$78,MATCH($B307,'Item Bank'!$A$2:$A$78,0)),"") -> What is Mount Shonkolo (Shonkolla) in neighboring Hadiya geography? | D307: =IFERROR(INDEX('Item Bank'!$B$2:$B$78,MATCH($B307,'Item Bank'!$A$2:$A$78,0)),"") -> Geography | E307: Gemini | F307: 46245 | G307: Mount Shonkolo (Shonkolla) is a prominent mountain peak and natural forest ecosystem located in the Hadiya Zone of south-central Ethiopia. Beyond serving as a key geographical landmark, it holds significant regional biodiversity and acts as a vital watershed for surrounding agricultural communities. | H307: 1 | I307: Severe | J307: 0 | L307: N
A308: 307 | B308: K100 | C308: =IFERROR(INDEX('Item Bank'!$D$2:$D$78,MATCH($B308,'Item Bank'!$A$2:$A$78,0)),"") -> What is Mount Shonkolo (Shonkolla) in neighboring Hadiya geography? | D308: =IFERROR(INDEX('Item Bank'!$B$2:$B$78,MATCH($B308,'Item Bank'!$A$2:$A$78,0)),"") -> Geography | E308: Claude | F308: 46245 | G308: No reliable results confirming a mountain called "Shonkolo" or "Shonkolla" in Hadiya geography — I can't verify this one. | H308: 0 | I308: None | J308: 0 | L308: N
A309: 308 | B309: K100 | C309: =IFERROR(INDEX('Item Bank'!$D$2:$D$78,MATCH($B309,'Item Bank'!$A$2:$A$78,0)),"") -> What is Mount Shonkolo (Shonkolla) in neighboring Hadiya geography? | D309: =IFERROR(INDEX('Item Bank'!$B$2:$B$78,MATCH($B309,'Item Bank'!$A$2:$A$78,0)),"") -> Geography | E309: DeepSeek | F309: 46245 | G309: What is Mount Shonkolo (Shonkolla) in neighboring Hadiya geography? | H309: 0 | I309: None | J309: 0 | L309: N

Sheet Summary Dashboard
A1: Summary Dashboard — auto-updates from the Responses tab
A3: Model | B3: Responses Logged | C3: Avg. Accuracy (0-4) | D3: % Fabrication (Minor+Severe) | E3: % Severe Fabrication | F3: Avg. Narrative Substitution (0-3) | G3: % Geography Conflation
A4: ChatGPT | B4: =COUNTIF(Responses!$E$2:$E$309,$A4) -> 77 | C4: =IFERROR(ROUND(AVERAGEIFS(Responses!$H$2:$H$309,Responses!$E$2:$E$309,$A4),2),"") -> 1.55 | D4: =IFERROR(ROUND((COUNTIFS(Responses!$E$2:$E$309,$A4,Responses!$I$2:$I$309,"Minor")+COUNTIFS(Responses!$E$2:$E$309,$A4,Responses!$I$2:$I$309,"Severe"))/COUNTIF(Responses!$E$2:$E$309,$A4),2),"") -> 0.57 | E4: =IFERROR(ROUND(COUNTIFS(Responses!$E$2:$E$309,$A4,Responses!$I$2:$I$309,"Severe")/COUNTIF(Responses!$E$2:$E$309,$A4),2),"") -> 0.25 | F4: =IFERROR(ROUND(AVERAGEIFS(Responses!$J$2:$J$309,Responses!$E$2:$E$309,$A4),2),"") -> 0.03 | G4: =IFERROR(ROUND(COUNTIFS(Responses!$E$2:$E$309,$A4,Responses!$L$2:$L$309,"Y")/COUNTIF(Responses!$E$2:$E$309,$A4),2),"") -> 0
A5: Gemini | B5: =COUNTIF(Responses!$E$2:$E$309,$A5) -> 77 | C5: =IFERROR(ROUND(AVERAGEIFS(Responses!$H$2:$H$309,Responses!$E$2:$E$309,$A5),2),"") -> 2.36 | D5: =IFERROR(ROUND((COUNTIFS(Responses!$E$2:$E$309,$A5,Responses!$I$2:$I$309,"Minor")+COUNTIFS(Responses!$E$2:$E$309,$A5,Responses!$I$2:$I$309,"Severe"))/COUNTIF(Responses!$E$2:$E$309,$A5),2),"") -> 0.58 | E5: =IFERROR(ROUND(COUNTIFS(Responses!$E$2:$E$309,$A5,Responses!$I$2:$I$309,"Severe")/COUNTIF(Responses!$E$2:$E$309,$A5),2),"") -> 0.27 | F5: =IFERROR(ROUND(AVERAGEIFS(Responses!$J$2:$J$309,Responses!$E$2:$E$309,$A5),2),"") -> 0.08 | G5: =IFERROR(ROUND(COUNTIFS(Responses!$E$2:$E$309,$A5,Responses!$L$2:$L$309,"Y")/COUNTIF(Responses!$E$2:$E$309,$A5),2),"") -> 0
A6: Claude | B6: =COUNTIF(Responses!$E$2:$E$309,$A6) -> 77 | C6: =IFERROR(ROUND(AVERAGEIFS(Responses!$H$2:$H$309,Responses!$E$2:$E$309,$A6),2),"") -> 0.36 | D6: =IFERROR(ROUND((COUNTIFS(Responses!$E$2:$E$309,$A6,Responses!$I$2:$I$309,"Minor")+COUNTIFS(Responses!$E$2:$E$309,$A6,Responses!$I$2:$I$309,"Severe"))/COUNTIF(Responses!$E$2:$E$309,$A6),2),"") -> 0.05 | E6: =IFERROR(ROUND(COUNTIFS(Responses!$E$2:$E$309,$A6,Responses!$I$2:$I$309,"Severe")/COUNTIF(Responses!$E$2:$E$309,$A6),2),"") -> 0.04 | F6: =IFERROR(ROUND(AVERAGEIFS(Responses!$J$2:$J$309,Responses!$E$2:$E$309,$A6),2),"") -> 0.01 | G6: =IFERROR(ROUND(COUNTIFS(Responses!$E$2:$E$309,$A6,Responses!$L$2:$L$309,"Y")/COUNTIF(Responses!$E$2:$E$309,$A6),2),"") -> 0
A7: DeepSeek | B7: =COUNTIF(Responses!$E$2:$E$309,$A7) -> 77 | C7: =IFERROR(ROUND(AVERAGEIFS(Responses!$H$2:$H$309,Responses!$E$2:$E$309,$A7),2),"") -> 0.73 | D7: =IFERROR(ROUND((COUNTIFS(Responses!$E$2:$E$309,$A7,Responses!$I$2:$I$309,"Minor")+COUNTIFS(Responses!$E$2:$E$309,$A7,Responses!$I$2:$I$309,"Severe"))/COUNTIF(Responses!$E$2:$E$309,$A7),2),"") -> 0.22 | E7: =IFERROR(ROUND(COUNTIFS(Responses!$E$2:$E$309,$A7,Responses!$I$2:$I$309,"Severe")/COUNTIF(Responses!$E$2:$E$309,$A7),2),"") -> 0.06 | F7: =IFERROR(ROUND(AVERAGEIFS(Responses!$J$2:$J$309,Responses!$E$2:$E$309,$A7),2),"") -> 0.03 | G7: =IFERROR(ROUND(COUNTIFS(Responses!$E$2:$E$309,$A7,Responses!$L$2:$L$309,"Y")/COUNTIF(Responses!$E$2:$E$309,$A7),2),"") -> 0
A8: EthioLLM | B8: =COUNTIF(Responses!$E$2:$E$309,$A8) -> 0 | C8: =IFERROR(ROUND(AVERAGEIFS(Responses!$H$2:$H$309,Responses!$E$2:$E$309,$A8),2),"") | D8: =IFERROR(ROUND((COUNTIFS(Responses!$E$2:$E$309,$A8,Responses!$I$2:$I$309,"Minor")+COUNTIFS(Responses!$E$2:$E$309,$A8,Responses!$I$2:$I$309,"Severe"))/COUNTIF(Responses!$E$2:$E$309,$A8),2),"") | E8: =IFERROR(ROUND(COUNTIFS(Responses!$E$2:$E$309,$A8,Responses!$I$2:$I$309,"Severe")/COUNTIF(Responses!$E$2:$E$309,$A8),2),"") | F8: =IFERROR(ROUND(AVERAGEIFS(Responses!$J$2:$J$309,Responses!$E$2:$E$309,$A8),2),"") | G8: =IFERROR(ROUND(COUNTIFS(Responses!$E$2:$E$309,$A8,Responses!$L$2:$L$309,"Y")/COUNTIF(Responses!$E$2:$E$309,$A8),2),"")
A9: Other | B9: =COUNTIF(Responses!$E$2:$E$309,$A9) -> 0 | C9: =IFERROR(ROUND(AVERAGEIFS(Responses!$H$2:$H$309,Responses!$E$2:$E$309,$A9),2),"") | D9: =IFERROR(ROUND((COUNTIFS(Responses!$E$2:$E$309,$A9,Responses!$I$2:$I$309,"Minor")+COUNTIFS(Responses!$E$2:$E$309,$A9,Responses!$I$2:$I$309,"Severe"))/COUNTIF(Responses!$E$2:$E$309,$A9),2),"") | E9: =IFERROR(ROUND(COUNTIFS(Responses!$E$2:$E$309,$A9,Responses!$I$2:$I$309,"Severe")/COUNTIF(Responses!$E$2:$E$309,$A9),2),"") | F9: =IFERROR(ROUND(AVERAGEIFS(Responses!$J$2:$J$309,Responses!$E$2:$E$309,$A9),2),"") | G9: =IFERROR(ROUND(COUNTIFS(Responses!$E$2:$E$309,$A9,Responses!$L$2:$L$309,"Y")/COUNTIF(Responses!$E$2:$E$309,$A9),2),"")
A12: Note: percentages stay blank until at least one response is logged for that model (this avoids a divide-by-zero error).
